{"ticketSingleList":[{"eterCode":"9337","DATE_ARRAY":"2025-05-12 (월),2025-05-13 (화),2025-05-14 (수),2025-05-15 (목),2025-05-16 (금),2025-05-17 (토),2025-05-18 (일),2025-05-19 (월),2025-05-20 (화),2025-05-21 (수),2025-05-22 (목),2025-05-23 (금),2025-05-24 (토),2025-05-25 (일),2025-05-26 (월),2025-05-27 (화),2025-05-28 (수),2025-05-29 (목),2025-05-30 (금),2025-05-31 (토),2025-06-01 (일),2025-06-02 (월),2025-06-03 (화),2025-06-04 (수),2025-06-05 (목),2025-06-06 (금),2025-06-07 (토),2025-06-08 (일),2025-06-09 (월),2025-06-10 (화),2025-06-11 (수)","DEP_DATE":"20250519","BUS_ORDER_CREATE_DAYS":30,"REMAIN_CNT":"27","DIST_TIME":0,"OPENGBN":"2","ARR_CD":"1","MOBILE_TICKET_CD":"2","ROUTE_DATA":"광릉내(진접)→진접센트레빌→정광산호→휴먼시아16단지→오남역→봉현마을(남양주)→내각농협→퇴계원(극동아파트)→별내역→신일유토빌→별내KCC→현대아이파크(별내)→인천공항→인천공항(제2터미널)","FARE_DC_CD":"0","BUS_TYPE_NM":"심야우등1","TRANSP_BIZR_ABBR_NM":"(주)경기고속","RESERVE_SEAT_CNT":0,"BUS_ROUTE_ID":"101841933703","DIV_CD":"1","DEP_TIME":"0225","SEAT_CODE":"0102-103,0405-106,0708-109,1011-112,1314-115,1617-118,1920-121,2223-124,25262728","sterCode":"1954","DISTANCE":0,"BLANK_CNT":"00","GUBUN_CD":"EBC","BUS_ORDER_DT":"20250519","SEAT_STATUS":"88888888888b8888888888888888","BUS_SEAT_TYPE":"y","RESERVE_DC_CNT":0,"STATION_TOT_CNT":8,"ROUTE_DEP_TM":"0200","RUN_CD":"1","TRANSP_BIZR_ID":"1100000","GROUP_DC_CNT":0,"TOT_SEAT_CNT":"28","FARE_DC_AMT":0,"RESERVATION_CHK":"1","BUS_TYPE":"m","FARE1":0,"FARE0":19300,"FARE3":9700,"FARE2":13500},{"eterCode":"9337","DATE_ARRAY":"2025-05-12 (월),2025-05-13 (화),2025-05-14 (수),2025-05-15 (목),2025-05-16 (금),2025-05-17 (토),2025-05-18 (일),2025-05-19 (월),2025-05-20 (화),2025-05-21 (수),2025-05-22 (목),2025-05-23 (금),2025-05-24 (토),2025-05-25 (일),2025-05-26 (월),2025-05-27 (화),2025-05-28 (수),2025-05-29 (목),2025-05-30 (금),2025-05-31 (토),2025-06-01 (일),2025-06-02 (월),2025-06-03 (화),2025-06-04 (수),2025-06-05 (목),2025-06-06 (금),2025-06-07 (토),2025-06-08 (일),2025-06-09 (월),2025-06-10 (화),2025-06-11 (수)","DEP_DATE":"20250519","BUS_ORDER_CREATE_DAYS":30,"REMAIN_CNT":"10","DIST_TIME":0,"OPENGBN":"2","ARR_CD":"1","MOBILE_TICKET_CD":"2","ROUTE_DATA":"광릉내(진접)→진접센트레빌→정광산호→휴먼시아16단지→오남역→봉현마을(남양주)→내각농협→퇴계원(극동아파트)→별내역→신일유토빌→별내KCC→현대아이파크(별내)→김포공항→인천공항→인천공항(제2터미널)","FARE_DC_CD":"0","BUS_TYPE_NM":"시외우등","TRANSP_BIZR_ABBR_NM":"(주)경기고속","RESERVE_SEAT_CNT":0,"BUS_ROUTE_ID":"101841933702","DIV_CD":"1","DEP_TIME":"0500","SEAT_CODE":"0102-103,0405-106,0708-109,1011-112,1314-115,1617-118,1920-121,2223-124,25262728","sterCode":"1954","DISTANCE":0,"BLANK_CNT":"00","GUBUN_CD":"EBC","BUS_ORDER_DT":"20250519","SEAT_STATUS":"8bbbbbbbb8bbbbb8bb8bb88b8888","BUS_SEAT_TYPE":"y","RESERVE_DC_CNT":0,"STATION_TOT_CNT":9,"ROUTE_DEP_TM":"0430","RUN_CD":"1","TRANSP_BIZR_ID":"1100000","GROUP_DC_CNT":0,"TOT_SEAT_CNT":"28","FARE_DC_AMT":0,"RESERVATION_CHK":"1","BUS_TYPE":"l","FARE1":0,"FARE0":16100,"FARE3":8100,"FARE2":11300},{"eterCode":"9337","DATE_ARRAY":"2025-05-12 (월),2025-05-13 (화),2025-05-14 (수),2025-05-15 (목),2025-05-16 (금),2025-05-17 (토),2025-05-18 (일),2025-05-19 (월),2025-05-20 (화),2025-05-21 (수),2025-05-22 (목),2025-05-23 (금),2025-05-24 (토),2025-05-25 (일),2025-05-26 (월),2025-05-27 (화),2025-05-28 (수),2025-05-29 (목),2025-05-30 (금),2025-05-31 (토),2025-06-01 (일),2025-06-02 (월),2025-06-03 (화),2025-06-04 (수),2025-06-05 (목),2025-06-06 (금),2025-06-07 (토),2025-06-08 (일),2025-06-09 (월),2025-06-10 (화),2025-06-11 (수)","DEP_DATE":"20250519","BUS_ORDER_CREATE_DAYS":30,"REMAIN_CNT":"21","DIST_TIME":0,"OPENGBN":"2","ARR_CD":"1","MOBILE_TICKET_CD":"2","ROUTE_DATA":"광릉내(진접)→진접센트레빌→정광산호→휴먼시아16단지→오남역→봉현마을(남양주)→내각농협→퇴계원(극동아파트)→별내역→신일유토빌→별내KCC→현대아이파크(별내)→김포공항→인천공항→인천공항(제2터미널)","FARE_DC_CD":"0","BUS_TYPE_NM":"시외우등","TRANSP_BIZR_ABBR_NM":"(주)경기고속","RESERVE_SEAT_CNT":0,"BUS_ROUTE_ID":"101841933702","DIV_CD":"1","DEP_TIME":"0730","SEAT_CODE":"0102-103,0405-106,0708-109,1011-112,1314-115,1617-118,1920-121,2223-124,25262728","sterCode":"1954","DISTANCE":0,"BLANK_CNT":"00","GUBUN_CD":"EBC","BUS_ORDER_DT":"20250519","SEAT_STATUS":"bb888bb8b88b88b8888888888888","BUS_SEAT_TYPE":"y","RESERVE_DC_CNT":0,"STATION_TOT_CNT":9,"ROUTE_DEP_TM":"0700","RUN_CD":"1","TRANSP_BIZR_ID":"1100000","GROUP_DC_CNT":0,"TOT_SEAT_CNT":"28","FARE_DC_AMT":0,"RESERVATION_CHK":"1","BUS_TYPE":"l","FARE1":0,"FARE0":16100,"FARE3":8100,"FARE2":11300},{"eterCode":"9337","DATE_ARRAY":"2025-05-12 (월),2025-05-13 (화),2025-05-14 (수),2025-05-15 (목),2025-05-16 (금),2025-05-17 (토),2025-05-18 (일),2025-05-19 (월),2025-05-20 (화),2025-05-21 (수),2025-05-22 (목),2025-05-23 (금),2025-05-24 (토),2025-05-25 (일),2025-05-26 (월),2025-05-27 (화),2025-05-28 (수),2025-05-29 (목),2025-05-30 (금),2025-05-31 (토),2025-06-01 (일),2025-06-02 (월),2025-06-03 (화),2025-06-04 (수),2025-06-05 (목),2025-06-06 (금),2025-06-07 (토),2025-06-08 (일),2025-06-09 (월),2025-06-10 (화),2025-06-11 (수)","DEP_DATE":"20250519","BUS_ORDER_CREATE_DAYS":30,"REMAIN_CNT":"24","DIST_TIME":0,"OPENGBN":"2","ARR_CD":"1","MOBILE_TICKET_CD":"2","ROUTE_DATA":"광릉내(진접)→진접센트레빌→정광산호→휴먼시아16단지→오남역→봉현마을(남양주)→내각농협→퇴계원(극동아파트)→별내역→신일유토빌→별내KCC→현대아이파크(별내)→김포공항→인천공항→인천공항(제2터미널)","FARE_DC_CD":"0","BUS_TYPE_NM":"시외우등","TRANSP_BIZR_ABBR_NM":"(주)경기고속","RESERVE_SEAT_CNT":0,"BUS_ROUTE_ID":"101841933702","DIV_CD":"1","DEP_TIME":"1300","SEAT_CODE":"0102-103,0405-106,0708-109,1011-112,1314-115,1617-118,1920-121,2223-124,25262728","sterCode":"1954","DISTANCE":0,"BLANK_CNT":"00","GUBUN_CD":"EBC","BUS_ORDER_DT":"20250519","SEAT_STATUS":"88888bbb888b8888888888888888","BUS_SEAT_TYPE":"y","RESERVE_DC_CNT":0,"STATION_TOT_CNT":9,"ROUTE_DEP_TM":"1230","RUN_CD":"1","TRANSP_BIZR_ID":"1100000","GROUP_DC_CNT":0,"TOT_SEAT_CNT":"28","FARE_DC_AMT":0,"RESERVATION_CHK":"1","BUS_TYPE":"l","FARE1":0,"FARE0":16100,"FARE3":8100,"FARE2":11300},{"eterCode":"9337","DATE_ARRAY":"2025-05-12 (월),2025-05-13 (화),2025-05-14 (수),2025-05-15 (목),2025-05-16 (금),2025-05-17 (토),2025-05-18 (일),2025-05-19 (월),2025-05-20 (화),2025-05-21 (수),2025-05-22 (목),2025-05-23 (금),2025-05-24 (토),2025-05-25 (일),2025-05-26 (월),2025-05-27 (화),2025-05-28 (수),2025-05-29 (목),2025-05-30 (금),2025-05-31 (토),2025-06-01 (일),2025-06-02 (월),2025-06-03 (화),2025-06-04 (수),2025-06-05 (목),2025-06-06 (금),2025-06-07 (토),2025-06-08 (일),2025-06-09 (월),2025-06-10 (화),2025-06-11 (수)","DEP_DATE":"20250519","BUS_ORDER_CREATE_DAYS":30,"REMAIN_CNT":"28","DIST_TIME":0,"OPENGBN":"2","ARR_CD":"1","MOBILE_TICKET_CD":"2","ROUTE_DATA":"광릉내(진접)→진접센트레빌→정광산호→휴먼시아16단지→오남역→봉현마을(남양주)→내각농협→퇴계원(극동아파트)→별내역→신일유토빌→별내KCC→현대아이파크(별내)→김포공항→인천공항→인천공항(제2터미널)","FARE_DC_CD":"0","BUS_TYPE_NM":"시외우등","TRANSP_BIZR_ABBR_NM":"(주)경기고속","RESERVE_SEAT_CNT":0,"BUS_ROUTE_ID":"101841933702","DIV_CD":"1","DEP_TIME":"1530","SEAT_CODE":"0102-103,0405-106,0708-109,1011-112,1314-115,1617-118,1920-121,2223-124,25262728","sterCode":"1954","DISTANCE":0,"BLANK_CNT":"00","GUBUN_CD":"EBC","BUS_ORDER_DT":"20250519","SEAT_STATUS":"8888888888888888888888888888","BUS_SEAT_TYPE":"y","RESERVE_DC_CNT":0,"STATION_TOT_CNT":9,"ROUTE_DEP_TM":"1500","RUN_CD":"1","TRANSP_BIZR_ID":"1100000","GROUP_DC_CNT":0,"TOT_SEAT_CNT":"28","FARE_DC_AMT":0,"RESERVATION_CHK":"1","BUS_TYPE":"l","FARE1":0,"FARE0":16100,"FARE3":8100,"FARE2":11300},{"eterCode":"9337","DATE_ARRAY":"2025-05-12 (월),2025-05-13 (화),2025-05-14 (수),2025-05-15 (목),2025-05-16 (금),2025-05-17 (토),2025-05-18 (일),2025-05-19 (월),2025-05-20 (화),2025-05-21 (수),2025-05-22 (목),2025-05-23 (금),2025-05-24 (토),2025-05-25 (일),2025-05-26 (월),2025-05-27 (화),2025-05-28 (수),2025-05-29 (목),2025-05-30 (금),2025-05-31 (토),2025-06-01 (일),2025-06-02 (월),2025-06-03 (화),2025-06-04 (수),2025-06-05 (목),2025-06-06 (금),2025-06-07 (토),2025-06-08 (일),2025-06-09 (월),2025-06-10 (화),2025-06-11 (수)","DEP_DATE":"20250519","BUS_ORDER_CREATE_DAYS":30,"REMAIN_CNT":"28","DIST_TIME":0,"OPENGBN":"2","ARR_CD":"1","MOBILE_TICKET_CD":"2","ROUTE_DATA":"광릉내(진접)→진접센트레빌→정광산호→휴먼시아16단지→오남역→봉현마을(남양주)→내각농협→퇴계원(극동아파트)→별내역→신일유토빌→별내KCC→현대아이파크(별내)→인천공항→인천공항(제2터미널)","FARE_DC_CD":"0","BUS_TYPE_NM":"시외우등","TRANSP_BIZR_ABBR_NM":"(주)경기고속","RESERVE_SEAT_CNT":0,"BUS_ROUTE_ID":"101841933703","DIV_CD":"1","DEP_TIME":"2155","SEAT_CODE":"0102-103,0405-106,0708-109,1011-112,1314-115,1617-118,1920-121,2223-124,25262728","sterCode":"1954","DISTANCE":0,"BLANK_CNT":"00","GUBUN_CD":"EBC","BUS_ORDER_DT":"20250519","SEAT_STATUS":"8888888888888888888888888888","BUS_SEAT_TYPE":"y","RESERVE_DC_CNT":0,"STATION_TOT_CNT":8,"ROUTE_DEP_TM":"2130","RUN_CD":"1","TRANSP_BIZR_ID":"1100000","GROUP_DC_CNT":0,"TOT_SEAT_CNT":"28","FARE_DC_AMT":0,"RESERVATION_CHK":"1","BUS_TYPE":"l","FARE1":0,"FARE0":16100,"FARE3":8100,"FARE2":11300}],"language":"kr","ticketDoubleList":[]}