{"ticketSingleList":[{"eterCode":"0004","DATE_ARRAY":"2025-05-16 (금),2025-05-17 (토),2025-05-18 (일),2025-05-19 (월),2025-05-20 (화),2025-05-21 (수),2025-05-22 (목),2025-05-23 (금),2025-05-24 (토),2025-05-25 (일),2025-05-26 (월),2025-05-27 (화),2025-05-28 (수),2025-05-29 (목),2025-05-30 (금),2025-05-31 (토)","DEP_DATE":"20250530","BUS_ORDER_CREATE_DAYS":15,"REMAIN_CNT":"27","DIST_TIME":170,"OPENGBN":"2","ARR_CD":"1","MOBILE_TICKET_CD":"1","ROUTE_DATA":"전주대→완주혁신도시→호남제일문→서울남부","FARE_DC_CD":"0","BUS_TYPE_NM":"일반","TRANSP_BIZR_ABBR_NM":"(유)호남고속","RESERVE_SEAT_CNT":2,"BUS_ROUTE_ID":"707099000402","DIV_CD":"0","DEP_TIME":"0800","SEAT_CODE":"010203,040506,070809,101112,131415,161718,192021,222324,252627,28293031","sterCode":"7099","DISTANCE":206,"BLANK_CNT":"00","GUBUN_CD":"EBC","BUS_ORDER_DT":"20250530","SEAT_STATUS":"8888888888f8f8888888b88b8888888","BUS_SEAT_TYPE":"8","RESERVE_DC_CNT":0,"STATION_TOT_CNT":4,"ROUTE_DEP_TM":"0800","RUN_CD":"1","TRANSP_BIZR_ID":"6300013","GROUP_DC_CNT":0,"TOT_SEAT_CNT":"31","FARE_DC_AMT":0,"RESERVATION_CHK":"1","BUS_TYPE":"1","FARE1":0,"FARE0":15000,"FARE3":7500,"FARE2":12000},{"eterCode":"0004","DATE_ARRAY":"2025-05-16 (금),2025-05-17 (토),2025-05-18 (일),2025-05-19 (월),2025-05-20 (화),2025-05-21 (수),2025-05-22 (목),2025-05-23 (금),2025-05-24 (토),2025-05-25 (일),2025-05-26 (월),2025-05-27 (화),2025-05-28 (수),2025-05-29 (목),2025-05-30 (금),2025-05-31 (토)","DEP_DATE":"20250530","BUS_ORDER_CREATE_DAYS":15,"REMAIN_CNT":"28","DIST_TIME":170,"OPENGBN":"2","ARR_CD":"1","MOBILE_TICKET_CD":"1","ROUTE_DATA":"전주대→완주혁신도시→호남제일문→서울남부","FARE_DC_CD":"0","BUS_TYPE_NM":"시외우등","TRANSP_BIZR_ABBR_NM":"㈜전북고속","RESERVE_SEAT_CNT":0,"BUS_ROUTE_ID":"707099000402","DIV_CD":"0","DEP_TIME":"0910","SEAT_CODE":"0102-103,0405-106,0708-109,1011-112,1314-115,1617-118,1920-121,2223-124,25262728","sterCode":"7099","DISTANCE":206,"BLANK_CNT":"00","GUBUN_CD":"EBC","BUS_ORDER_DT":"20250530","SEAT_STATUS":"8888888888888888888888888888","BUS_SEAT_TYPE":"y","RESERVE_DC_CNT":0,"STATION_TOT_CNT":4,"ROUTE_DEP_TM":"0910","RUN_CD":"1","TRANSP_BIZR_ID":"6300011","GROUP_DC_CNT":0,"TOT_SEAT_CNT":"28","FARE_DC_AMT":0,"RESERVATION_CHK":"1","BUS_TYPE":"l","FARE1":0,"FARE0":19000,"FARE3":9500,"FARE2":15200},{"eterCode":"0004","DATE_ARRAY":"2025-05-16 (금),2025-05-17 (토),2025-05-18 (일),2025-05-19 (월),2025-05-20 (화),2025-05-21 (수),2025-05-22 (목),2025-05-23 (금),2025-05-24 (토),2025-05-25 (일),2025-05-26 (월),2025-05-27 (화),2025-05-28 (수),2025-05-29 (목),2025-05-30 (금),2025-05-31 (토)","DEP_DATE":"20250530","BUS_ORDER_CREATE_DAYS":15,"REMAIN_CNT":"28","DIST_TIME":170,"OPENGBN":"2","ARR_CD":"1","MOBILE_TICKET_CD":"1","ROUTE_DATA":"전주대→완주혁신도시→호남제일문→서울남부","FARE_DC_CD":"0","BUS_TYPE_NM":"시외우등","TRANSP_BIZR_ABBR_NM":"(유)호남고속","RESERVE_SEAT_CNT":0,"BUS_ROUTE_ID":"707099000402","DIV_CD":"0","DEP_TIME":"1020","SEAT_CODE":"0102-103,0405-106,0708-109,1011-112,1314-115,1617-118,1920-121,2223-124,25262728","sterCode":"7099","DISTANCE":206,"BLANK_CNT":"00","GUBUN_CD":"EBC","BUS_ORDER_DT":"20250530","SEAT_STATUS":"8888888888888888888888888888","BUS_SEAT_TYPE":"y","RESERVE_DC_CNT":0,"STATION_TOT_CNT":4,"ROUTE_DEP_TM":"1020","RUN_CD":"1","TRANSP_BIZR_ID":"6300013","GROUP_DC_CNT":0,"TOT_SEAT_CNT":"28","FARE_DC_AMT":0,"RESERVATION_CHK":"1","BUS_TYPE":"l","FARE1":0,"FARE0":19000,"FARE3":9500,"FARE2":15200},{"eterCode":"0004","DATE_ARRAY":"2025-05-16 (금),2025-05-17 (토),2025-05-18 (일),2025-05-19 (월),2025-05-20 (화),2025-05-21 (수),2025-05-22 (목),2025-05-23 (금),2025-05-24 (토),2025-05-25 (일),2025-05-26 (월),2025-05-27 (화),2025-05-28 (수),2025-05-29 (목),2025-05-30 (금),2025-05-31 (토)","DEP_DATE":"20250530","BUS_ORDER_CREATE_DAYS":15,"REMAIN_CNT":"28","DIST_TIME":170,"OPENGBN":"2","ARR_CD":"1","MOBILE_TICKET_CD":"1","ROUTE_DATA":"전주대→완주혁신도시→호남제일문→서울남부","FARE_DC_CD":"0","BUS_TYPE_NM":"시외우등","TRANSP_BIZR_ABBR_NM":"㈜전북고속","RESERVE_SEAT_CNT":0,"BUS_ROUTE_ID":"707099000402","DIV_CD":"0","DEP_TIME":"1130","SEAT_CODE":"0102-103,0405-106,0708-109,1011-112,1314-115,1617-118,1920-121,2223-124,25262728","sterCode":"7099","DISTANCE":206,"BLANK_CNT":"00","GUBUN_CD":"EBC","BUS_ORDER_DT":"20250530","SEAT_STATUS":"8888888888888888888888888888","BUS_SEAT_TYPE":"y","RESERVE_DC_CNT":0,"STATION_TOT_CNT":4,"ROUTE_DEP_TM":"1130","RUN_CD":"1","TRANSP_BIZR_ID":"6300011","GROUP_DC_CNT":0,"TOT_SEAT_CNT":"28","FARE_DC_AMT":0,"RESERVATION_CHK":"1","BUS_TYPE":"l","FARE1":0,"FARE0":19000,"FARE3":9500,"FARE2":15200},{"eterCode":"0004","DATE_ARRAY":"2025-05-16 (금),2025-05-17 (토),2025-05-18 (일),2025-05-19 (월),2025-05-20 (화),2025-05-21 (수),2025-05-22 (목),2025-05-23 (금),2025-05-24 (토),2025-05-25 (일),2025-05-26 (월),2025-05-27 (화),2025-05-28 (수),2025-05-29 (목),2025-05-30 (금),2025-05-31 (토)","DEP_DATE":"20250530","BUS_ORDER_CREATE_DAYS":15,"REMAIN_CNT":"41","DIST_TIME":170,"OPENGBN":"2","ARR_CD":"1","MOBILE_TICKET_CD":"1","ROUTE_DATA":"전주대→완주혁신도시→호남제일문→서울남부","FARE_DC_CD":"0","BUS_TYPE_NM":"일반","TRANSP_BIZR_ABBR_NM":"㈜전북고속","RESERVE_SEAT_CNT":0,"BUS_ROUTE_ID":"707099000402","DIV_CD":"0","DEP_TIME":"1340","SEAT_CODE":"01020304,05060708,09101112,13141516,17181920,21222324,25262728,29303132,33343536,3738394041","sterCode":"7099","DISTANCE":206,"BLANK_CNT":"00","GUBUN_CD":"EBC","BUS_ORDER_DT":"20250530","SEAT_STATUS":"88888888888888888888888888888888888888888","BUS_SEAT_TYPE":"h","RESERVE_DC_CNT":0,"STATION_TOT_CNT":4,"ROUTE_DEP_TM":"1340","RUN_CD":"1","TRANSP_BIZR_ID":"6300011","GROUP_DC_CNT":0,"TOT_SEAT_CNT":"41","FARE_DC_AMT":0,"RESERVATION_CHK":"1","BUS_TYPE":"1","FARE1":0,"FARE0":15000,"FARE3":7500,"FARE2":12000},{"eterCode":"0004","DATE_ARRAY":"2025-05-16 (금),2025-05-17 (토),2025-05-18 (일),2025-05-19 (월),2025-05-20 (화),2025-05-21 (수),2025-05-22 (목),2025-05-23 (금),2025-05-24 (토),2025-05-25 (일),2025-05-26 (월),2025-05-27 (화),2025-05-28 (수),2025-05-29 (목),2025-05-30 (금),2025-05-31 (토)","DEP_DATE":"20250530","BUS_ORDER_CREATE_DAYS":15,"REMAIN_CNT":"39","DIST_TIME":170,"OPENGBN":"2","ARR_CD":"1","MOBILE_TICKET_CD":"1","ROUTE_DATA":"전주대→완주혁신도시→호남제일문→서울남부","FARE_DC_CD":"0","BUS_TYPE_NM":"일반","TRANSP_BIZR_ABBR_NM":"㈜전북고속","RESERVE_SEAT_CNT":2,"BUS_ROUTE_ID":"707099000402","DIV_CD":"0","DEP_TIME":"1440","SEAT_CODE":"01020304,05060708,09101112,13141516,17181920,21222324,25262728,29303132,33343536,3738394041","sterCode":"7099","DISTANCE":206,"BLANK_CNT":"00","GUBUN_CD":"EBC","BUS_ORDER_DT":"20250530","SEAT_STATUS":"8888888888888888ff88888888888888888888888","BUS_SEAT_TYPE":"h","RESERVE_DC_CNT":0,"STATION_TOT_CNT":4,"ROUTE_DEP_TM":"1440","RUN_CD":"1","TRANSP_BIZR_ID":"6300011","GROUP_DC_CNT":0,"TOT_SEAT_CNT":"41","FARE_DC_AMT":0,"RESERVATION_CHK":"1","BUS_TYPE":"1","FARE1":0,"FARE0":15000,"FARE3":7500,"FARE2":12000},{"eterCode":"0004","DATE_ARRAY":"2025-05-16 (금),2025-05-17 (토),2025-05-18 (일),2025-05-19 (월),2025-05-20 (화),2025-05-21 (수),2025-05-22 (목),2025-05-23 (금),2025-05-24 (토),2025-05-25 (일),2025-05-26 (월),2025-05-27 (화),2025-05-28 (수),2025-05-29 (목),2025-05-30 (금),2025-05-31 (토)","DEP_DATE":"20250530","BUS_ORDER_CREATE_DAYS":15,"REMAIN_CNT":"27","DIST_TIME":170,"OPENGBN":"2","ARR_CD":"1","MOBILE_TICKET_CD":"1","ROUTE_DATA":"전주대→완주혁신도시→호남제일문→서울남부","FARE_DC_CD":"0","BUS_TYPE_NM":"시외우등","TRANSP_BIZR_ABBR_NM":"(유)호남고속","RESERVE_SEAT_CNT":1,"BUS_ROUTE_ID":"707099000402","DIV_CD":"0","DEP_TIME":"1540","SEAT_CODE":"0102-103,0405-106,0708-109,1011-112,1314-115,1617-118,1920-121,2223-124,25262728","sterCode":"7099","DISTANCE":206,"BLANK_CNT":"00","GUBUN_CD":"EBC","BUS_ORDER_DT":"20250530","SEAT_STATUS":"88f8888888888888888888888888","BUS_SEAT_TYPE":"y","RESERVE_DC_CNT":0,"STATION_TOT_CNT":4,"ROUTE_DEP_TM":"1540","RUN_CD":"1","TRANSP_BIZR_ID":"6300013","GROUP_DC_CNT":0,"TOT_SEAT_CNT":"28","FARE_DC_AMT":0,"RESERVATION_CHK":"1","BUS_TYPE":"l","FARE1":0,"FARE0":19000,"FARE3":9500,"FARE2":15200},{"eterCode":"0004","DATE_ARRAY":"2025-05-16 (금),2025-05-17 (토),2025-05-18 (일),2025-05-19 (월),2025-05-20 (화),2025-05-21 (수),2025-05-22 (목),2025-05-23 (금),2025-05-24 (토),2025-05-25 (일),2025-05-26 (월),2025-05-27 (화),2025-05-28 (수),2025-05-29 (목),2025-05-30 (금),2025-05-31 (토)","DEP_DATE":"20250530","BUS_ORDER_CREATE_DAYS":15,"REMAIN_CNT":"26","DIST_TIME":170,"OPENGBN":"2","ARR_CD":"1","MOBILE_TICKET_CD":"1","ROUTE_DATA":"전주대→완주혁신도시→호남제일문→서울남부","FARE_DC_CD":"0","BUS_TYPE_NM":"일반","TRANSP_BIZR_ABBR_NM":"(유)호남고속","RESERVE_SEAT_CNT":1,"BUS_ROUTE_ID":"707099000402","DIV_CD":"0","DEP_TIME":"1700","SEAT_CODE":"010203,040506,070809,101112,131415,161718,192021,222324,252627,28293031","sterCode":"7099","DISTANCE":206,"BLANK_CNT":"00","GUBUN_CD":"EBC","BUS_ORDER_DT":"20250530","SEAT_STATUS":"88b88888888b88f88b88b8888888888","BUS_SEAT_TYPE":"8","RESERVE_DC_CNT":0,"STATION_TOT_CNT":4,"ROUTE_DEP_TM":"1700","RUN_CD":"1","TRANSP_BIZR_ID":"6300013","GROUP_DC_CNT":0,"TOT_SEAT_CNT":"31","FARE_DC_AMT":0,"RESERVATION_CHK":"1","BUS_TYPE":"1","FARE1":0,"FARE0":15000,"FARE3":7500,"FARE2":12000},{"eterCode":"0004","DATE_ARRAY":"2025-05-16 (금),2025-05-17 (토),2025-05-18 (일),2025-05-19 (월),2025-05-20 (화),2025-05-21 (수),2025-05-22 (목),2025-05-23 (금),2025-05-24 (토),2025-05-25 (일),2025-05-26 (월),2025-05-27 (화),2025-05-28 (수),2025-05-29 (목),2025-05-30 (금),2025-05-31 (토)","DEP_DATE":"20250530","BUS_ORDER_CREATE_DAYS":15,"REMAIN_CNT":"41","DIST_TIME":170,"OPENGBN":"2","ARR_CD":"1","MOBILE_TICKET_CD":"1","ROUTE_DATA":"전주대→완주혁신도시→호남제일문→서울남부","FARE_DC_CD":"0","BUS_TYPE_NM":"일반","TRANSP_BIZR_ABBR_NM":"㈜전북고속","RESERVE_SEAT_CNT":0,"BUS_ROUTE_ID":"707099000402","DIV_CD":"0","DEP_TIME":"1740","SEAT_CODE":"01020304,05060708,09101112,13141516,17181920,21222324,25262728,29303132,33343536,3738394041","sterCode":"7099","DISTANCE":206,"BLANK_CNT":"00","GUBUN_CD":"EBC","BUS_ORDER_DT":"20250530","SEAT_STATUS":"88888888888888888888888888888888888888888","BUS_SEAT_TYPE":"h","RESERVE_DC_CNT":0,"STATION_TOT_CNT":4,"ROUTE_DEP_TM":"1740","RUN_CD":"1","TRANSP_BIZR_ID":"6300011","GROUP_DC_CNT":0,"TOT_SEAT_CNT":"41","FARE_DC_AMT":0,"RESERVATION_CHK":"1","BUS_TYPE":"1","FARE1":0,"FARE0":15000,"FARE3":7500,"FARE2":12000},{"eterCode":"0004","DATE_ARRAY":"2025-05-16 (금),2025-05-17 (토),2025-05-18 (일),2025-05-19 (월),2025-05-20 (화),2025-05-21 (수),2025-05-22 (목),2025-05-23 (금),2025-05-24 (토),2025-05-25 (일),2025-05-26 (월),2025-05-27 (화),2025-05-28 (수),2025-05-29 (목),2025-05-30 (금),2025-05-31 (토)","DEP_DATE":"20250530","BUS_ORDER_CREATE_DAYS":15,"REMAIN_CNT":"28","DIST_TIME":170,"OPENGBN":"2","ARR_CD":"1","MOBILE_TICKET_CD":"1","ROUTE_DATA":"전주대→완주혁신도시→호남제일문→서울남부","FARE_DC_CD":"0","BUS_TYPE_NM":"시외우등","TRANSP_BIZR_ABBR_NM":"(유)호남고속","RESERVE_SEAT_CNT":0,"BUS_ROUTE_ID":"707099000402","DIV_CD":"0","DEP_TIME":"1820","SEAT_CODE":"0102-103,0405-106,0708-109,1011-112,1314-115,1617-118,1920-121,2223-124,25262728","sterCode":"7099","DISTANCE":206,"BLANK_CNT":"00","GUBUN_CD":"EBC","BUS_ORDER_DT":"20250530","SEAT_STATUS":"8888888888888888888888888888","BUS_SEAT_TYPE":"y","RESERVE_DC_CNT":0,"STATION_TOT_CNT":4,"ROUTE_DEP_TM":"1820","RUN_CD":"1","TRANSP_BIZR_ID":"6300013","GROUP_DC_CNT":0,"TOT_SEAT_CNT":"28","FARE_DC_AMT":0,"RESERVATION_CHK":"1","BUS_TYPE":"l","FARE1":0,"FARE0":19000,"FARE3":9500,"FARE2":15200},{"eterCode":"0004","DATE_ARRAY":"2025-05-16 (금),2025-05-17 (토),2025-05-18 (일),2025-05-19 (월),2025-05-20 (화),2025-05-21 (수),2025-05-22 (목),2025-05-23 (금),2025-05-24 (토),2025-05-25 (일),2025-05-26 (월),2025-05-27 (화),2025-05-28 (수),2025-05-29 (목),2025-05-30 (금),2025-05-31 (토)","DEP_DATE":"20250530","BUS_ORDER_CREATE_DAYS":15,"REMAIN_CNT":"28","DIST_TIME":170,"OPENGBN":"2","ARR_CD":"1","MOBILE_TICKET_CD":"1","ROUTE_DATA":"전주대→완주혁신도시→호남제일문→서울남부","FARE_DC_CD":"0","BUS_TYPE_NM":"시외우등","TRANSP_BIZR_ABBR_NM":"㈜전북고속","RESERVE_SEAT_CNT":0,"BUS_ROUTE_ID":"707099000402","DIV_CD":"0","DEP_TIME":"1930","SEAT_CODE":"0102-103,0405-106,0708-109,1011-112,1314-115,1617-118,1920-121,2223-124,25262728","sterCode":"7099","DISTANCE":206,"BLANK_CNT":"00","GUBUN_CD":"EBC","BUS_ORDER_DT":"20250530","SEAT_STATUS":"8888888888888888888888888888","BUS_SEAT_TYPE":"y","RESERVE_DC_CNT":0,"STATION_TOT_CNT":4,"ROUTE_DEP_TM":"1930","RUN_CD":"1","TRANSP_BIZR_ID":"6300011","GROUP_DC_CNT":0,"TOT_SEAT_CNT":"28","FARE_DC_AMT":0,"RESERVATION_CHK":"1","BUS_TYPE":"l","FARE1":0,"FARE0":19000,"FARE3":9500,"FARE2":15200}],"language":"kr","ticketDoubleList":[]}