{"created":"2025-06-21T20:18:12.800Z","expires":"2025-07-05T20:18:12.800Z","data":"{\"ticketSingleList\":[{\"eterCode\":\"7009\",\"DATE_ARRAY\":\"2025-06-22 (일),2025-06-23 (월),2025-06-24 (화),2025-06-25 (수),2025-06-26 (목),2025-06-27 (금),2025-06-28 (토),2025-06-29 (일)\",\"DEP_DATE\":\"20250624\",\"BUS_ORDER_CREATE_DAYS\":7,\"REMAIN_CNT\":\"00\",\"DIST_TIME\":0,\"OPENGBN\":\"2\",\"ARR_CD\":\"1\",\"MOBILE_TICKET_CD\":\"0\",\"ROUTE_DATA\":\"효자동→김제→부안\",\"FARE_DC_CD\":\"0\",\"BUS_TYPE_NM\":\"일반\",\"TRANSP_BIZR_ABBR_NM\":\"㈜전북고속\",\"RESERVE_SEAT_CNT\":0,\"BUS_ROUTE_ID\":\"707341701801\",\"DIV_CD\":\"1\",\"DEP_TIME\":\"0630\",\"sterCode\":\"7341\",\"DISTANCE\":0,\"BLANK_CNT\":\"00\",\"GUBUN_CD\":\"EBC\",\"BUS_ORDER_DT\":\"20250624\",\"RESERVE_DC_CNT\":0,\"STATION_TOT_CNT\":2,\"ROUTE_DEP_TM\":\"0630\",\"RUN_CD\":\"1\",\"TRANSP_BIZR_ID\":\"6300011\",\"GROUP_DC_CNT\":0,\"TOT_SEAT_CNT\":\"00\",\"FARE_DC_AMT\":0,\"RESERVATION_CHK\":\"1\",\"BUS_TYPE\":\"1\",\"FARE1\":0,\"FARE0\":3200,\"FARE3\":1600,\"FARE2\":2600},{\"eterCode\":\"7009\",\"DATE_ARRAY\":\"2025-06-22 (일),2025-06-23 (월),2025-06-24 (화),2025-06-25 (수),2025-06-26 (목),2025-06-27 (금),2025-06-28 (토),2025-06-29 (일)\",\"DEP_DATE\":\"20250624\",\"BUS_ORDER_CREATE_DAYS\":7,\"REMAIN_CNT\":\"00\",\"DIST_TIME\":0,\"OPENGBN\":\"2\",\"ARR_CD\":\"1\",\"MOBILE_TICKET_CD\":\"0\",\"ROUTE_DATA\":\"효자동→김제→부안\",\"FARE_DC_CD\":\"0\",\"BUS_TYPE_NM\":\"일반\",\"TRANSP_BIZR_ABBR_NM\":\"㈜전주고속\",\"RESERVE_SEAT_CNT\":0,\"BUS_ROUTE_ID\":\"707341701801\",\"DIV_CD\":\"1\",\"DEP_TIME\":\"0645\",\"sterCode\":\"7341\",\"DISTANCE\":0,\"BLANK_CNT\":\"00\",\"GUBUN_CD\":\"EBC\",\"BUS_ORDER_DT\":\"20250624\",\"RESERVE_DC_CNT\":0,\"STATION_TOT_CNT\":2,\"ROUTE_DEP_TM\":\"0645\",\"RUN_CD\":\"1\",\"TRANSP_BIZR_ID\":\"6300012\",\"GROUP_DC_CNT\":0,\"TOT_SEAT_CNT\":\"00\",\"FARE_DC_AMT\":0,\"RESERVATION_CHK\":\"1\",\"BUS_TYPE\":\"1\",\"FARE1\":0,\"FARE0\":3200,\"FARE3\":1600,\"FARE2\":2600},{\"eterCode\":\"7009\",\"DATE_ARRAY\":\"2025-06-22 (일),2025-06-23 (월),2025-06-24 (화),2025-06-25 (수),2025-06-26 (목),2025-06-27 (금),2025-06-28 (토),2025-06-29 (일)\",\"DEP_DATE\":\"20250624\",\"BUS_ORDER_CREATE_DAYS\":7,\"REMAIN_CNT\":\"00\",\"DIST_TIME\":0,\"OPENGBN\":\"2\",\"ARR_CD\":\"1\",\"MOBILE_TICKET_CD\":\"0\",\"ROUTE_DATA\":\"효자동→김제→부안\",\"FARE_DC_CD\":\"0\",\"BUS_TYPE_NM\":\"일반\",\"TRANSP_BIZR_ABBR_NM\":\"㈜전북고속\",\"RESERVE_SEAT_CNT\":0,\"BUS_ROUTE_ID\":\"707341701801\",\"DIV_CD\":\"1\",\"DEP_TIME\":\"0700\",\"sterCode\":\"7341\",\"DISTANCE\":0,\"BLANK_CNT\":\"00\",\"GUBUN_CD\":\"EBC\",\"BUS_ORDER_DT\":\"20250624\",\"RESERVE_DC_CNT\":0,\"STATION_TOT_CNT\":2,\"ROUTE_DEP_TM\":\"0700\",\"RUN_CD\":\"1\",\"TRANSP_BIZR_ID\":\"6300011\",\"GROUP_DC_CNT\":0,\"TOT_SEAT_CNT\":\"00\",\"FARE_DC_AMT\":0,\"RESERVATION_CHK\":\"1\",\"BUS_TYPE\":\"1\",\"FARE1\":0,\"FARE0\":3200,\"FARE3\":1600,\"FARE2\":2600},{\"eterCode\":\"7009\",\"DATE_ARRAY\":\"2025-06-22 (일),2025-06-23 (월),2025-06-24 (화),2025-06-25 (수),2025-06-26 (목),2025-06-27 (금),2025-06-28 (토),2025-06-29 (일)\",\"DEP_DATE\":\"20250624\",\"BUS_ORDER_CREATE_DAYS\":7,\"REMAIN_CNT\":\"00\",\"DIST_TIME\":0,\"OPENGBN\":\"2\",\"ARR_CD\":\"1\",\"MOBILE_TICKET_CD\":\"0\",\"ROUTE_DATA\":\"효자동→김제\",\"FARE_DC_CD\":\"0\",\"BUS_TYPE_NM\":\"일반\",\"TRANSP_BIZR_ABBR_NM\":\"전북여객(주)\",\"RESERVE_SEAT_CNT\":0,\"BUS_ROUTE_ID\":\"707341700901\",\"DIV_CD\":\"1\",\"DEP_TIME\":\"0709\",\"sterCode\":\"7341\",\"DISTANCE\":0,\"BLANK_CNT\":\"00\",\"GUBUN_CD\":\"EBC\",\"BUS_ORDER_DT\":\"20250624\",\"RESERVE_DC_CNT\":0,\"STATION_TOT_CNT\":2,\"ROUTE_DEP_TM\":\"0709\",\"RUN_CD\":\"1\",\"TRANSP_BIZR_ID\":\"6300016\",\"GROUP_DC_CNT\":0,\"TOT_SEAT_CNT\":\"00\",\"FARE_DC_AMT\":0,\"RESERVATION_CHK\":\"1\",\"BUS_TYPE\":\"1\",\"FARE1\":0,\"FARE0\":3200,\"FARE3\":1600,\"FARE2\":2600},{\"eterCode\":\"7009\",\"DATE_ARRAY\":\"2025-06-22 (일),2025-06-23 (월),2025-06-24 (화),2025-06-25 (수),2025-06-26 (목),2025-06-27 (금),2025-06-28 (토),2025-06-29 (일)\",\"DEP_DATE\":\"20250624\",\"BUS_ORDER_CREATE_DAYS\":7,\"REMAIN_CNT\":\"00\",\"DIST_TIME\":0,\"OPENGBN\":\"2\",\"ARR_CD\":\"1\",\"MOBILE_TICKET_CD\":\"0\",\"ROUTE_DATA\":\"효자동→김제→부안\",\"FARE_DC_CD\":\"0\",\"BUS_TYPE_NM\":\"일반\",\"TRANSP_BIZR_ABBR_NM\":\"㈜전주고속\",\"RESERVE_SEAT_CNT\":0,\"BUS_ROUTE_ID\":\"707341701801\",\"DIV_CD\":\"1\",\"DEP_TIME\":\"0725\",\"sterCode\":\"7341\",\"DISTANCE\":0,\"BLANK_CNT\":\"00\",\"GUBUN_CD\":\"EBC\",\"BUS_ORDER_DT\":\"20250624\",\"RESERVE_DC_CNT\":0,\"STATION_TOT_CNT\":2,\"ROUTE_DEP_TM\":\"0725\",\"RUN_CD\":\"1\",\"TRANSP_BIZR_ID\":\"6300012\",\"GROUP_DC_CNT\":0,\"TOT_SEAT_CNT\":\"00\",\"FARE_DC_AMT\":0,\"RESERVATION_CHK\":\"1\",\"BUS_TYPE\":\"1\",\"FARE1\":0,\"FARE0\":3200,\"FARE3\":1600,\"FARE2\":2600},{\"eterCode\":\"7009\",\"DATE_ARRAY\":\"2025-06-22 (일),2025-06-23 (월),2025-06-24 (화),2025-06-25 (수),2025-06-26 (목),2025-06-27 (금),2025-06-28 (토),2025-06-29 (일)\",\"DEP_DATE\":\"20250624\",\"BUS_ORDER_CREATE_DAYS\":7,\"REMAIN_CNT\":\"00\",\"DIST_TIME\":0,\"OPENGBN\":\"2\",\"ARR_CD\":\"1\",\"MOBILE_TICKET_CD\":\"0\",\"ROUTE_DATA\":\"효자동→김제\",\"FARE_DC_CD\":\"0\",\"BUS_TYPE_NM\":\"일반\",\"TRANSP_BIZR_ABBR_NM\":\"전북여객(주)\",\"RESERVE_SEAT_CNT\":0,\"BUS_ROUTE_ID\":\"707341700901\",\"DIV_CD\":\"1\",\"DEP_TIME\":\"0734\",\"sterCode\":\"7341\",\"DISTANCE\":0,\"BLANK_CNT\":\"00\",\"GUBUN_CD\":\"EBC\",\"BUS_ORDER_DT\":\"20250624\",\"RESERVE_DC_CNT\":0,\"STATION_TOT_CNT\":2,\"ROUTE_DEP_TM\":\"0734\",\"RUN_CD\":\"1\",\"TRANSP_BIZR_ID\":\"6300016\",\"GROUP_DC_CNT\":0,\"TOT_SEAT_CNT\":\"00\",\"FARE_DC_AMT\":0,\"RESERVATION_CHK\":\"1\",\"BUS_TYPE\":\"1\",\"FARE1\":0,\"FARE0\":3200,\"FARE3\":1600,\"FARE2\":2600},{\"eterCode\":\"7009\",\"DATE_ARRAY\":\"2025-06-22 (일),2025-06-23 (월),2025-06-24 (화),2025-06-25 (수),2025-06-26 (목),2025-06-27 (금),2025-06-28 (토),2025-06-29 (일)\",\"DEP_DATE\":\"20250624\",\"BUS_ORDER_CREATE_DAYS\":7,\"REMAIN_CNT\":\"00\",\"DIST_TIME\":0,\"OPENGBN\":\"2\",\"ARR_CD\":\"1\",\"MOBILE_TICKET_CD\":\"0\",\"ROUTE_DATA\":\"효자동→김제→부안\",\"FARE_DC_CD\":\"0\",\"BUS_TYPE_NM\":\"일반\",\"TRANSP_BIZR_ABBR_NM\":\"㈜전주고속\",\"RESERVE_SEAT_CNT\":0,\"BUS_ROUTE_ID\":\"707341701801\",\"DIV_CD\":\"1\",\"DEP_TIME\":\"0750\",\"sterCode\":\"7341\",\"DISTANCE\":0,\"BLANK_CNT\":\"00\",\"GUBUN_CD\":\"EBC\",\"BUS_ORDER_DT\":\"20250624\",\"RESERVE_DC_CNT\":0,\"STATION_TOT_CNT\":2,\"ROUTE_DEP_TM\":\"0750\",\"RUN_CD\":\"1\",\"TRANSP_BIZR_ID\":\"6300012\",\"GROUP_DC_CNT\":0,\"TOT_SEAT_CNT\":\"00\",\"FARE_DC_AMT\":0,\"RESERVATION_CHK\":\"1\",\"BUS_TYPE\":\"1\",\"FARE1\":0,\"FARE0\":3200,\"FARE3\":1600,\"FARE2\":2600},{\"eterCode\":\"7009\",\"DATE_ARRAY\":\"2025-06-22 (일),2025-06-23 (월),2025-06-24 (화),2025-06-25 (수),2025-06-26 (목),2025-06-27 (금),2025-06-28 (토),2025-06-29 (일)\",\"DEP_DATE\":\"20250624\",\"BUS_ORDER_CREATE_DAYS\":7,\"REMAIN_CNT\":\"00\",\"DIST_TIME\":0,\"OPENGBN\":\"2\",\"ARR_CD\":\"1\",\"MOBILE_TICKET_CD\":\"0\",\"ROUTE_DATA\":\"효자동→김제\",\"FARE_DC_CD\":\"0\",\"BUS_TYPE_NM\":\"일반\",\"TRANSP_BIZR_ABBR_NM\":\"전북여객(주)\",\"RESERVE_SEAT_CNT\":0,\"BUS_ROUTE_ID\":\"707341700901\",\"DIV_CD\":\"1\",\"DEP_TIME\":\"0759\",\"sterCode\":\"7341\",\"DISTANCE\":0,\"BLANK_CNT\":\"00\",\"GUBUN_CD\":\"EBC\",\"BUS_ORDER_DT\":\"20250624\",\"RESERVE_DC_CNT\":0,\"STATION_TOT_CNT\":2,\"ROUTE_DEP_TM\":\"0759\",\"RUN_CD\":\"1\",\"TRANSP_BIZR_ID\":\"6300016\",\"GROUP_DC_CNT\":0,\"TOT_SEAT_CNT\":\"00\",\"FARE_DC_AMT\":0,\"RESERVATION_CHK\":\"1\",\"BUS_TYPE\":\"1\",\"FARE1\":0,\"FARE0\":3200,\"FARE3\":1600,\"FARE2\":2600},{\"eterCode\":\"7009\",\"DATE_ARRAY\":\"2025-06-22 (일),2025-06-23 (월),2025-06-24 (화),2025-06-25 (수),2025-06-26 (목),2025-06-27 (금),2025-06-28 (토),2025-06-29 (일)\",\"DEP_DATE\":\"20250624\",\"BUS_ORDER_CREATE_DAYS\":7,\"REMAIN_CNT\":\"00\",\"DIST_TIME\":0,\"OPENGBN\":\"2\",\"ARR_CD\":\"1\",\"MOBILE_TICKET_CD\":\"0\",\"ROUTE_DATA\":\"효자동→김제→부안\",\"FARE_DC_CD\":\"0\",\"BUS_TYPE_NM\":\"일반\",\"TRANSP_BIZR_ABBR_NM\":\"㈜전주고속\",\"RESERVE_SEAT_CNT\":0,\"BUS_ROUTE_ID\":\"707341701801\",\"DIV_CD\":\"1\",\"DEP_TIME\":\"0815\",\"sterCode\":\"7341\",\"DISTANCE\":0,\"BLANK_CNT\":\"00\",\"GUBUN_CD\":\"EBC\",\"BUS_ORDER_DT\":\"20250624\",\"RESERVE_DC_CNT\":0,\"STATION_TOT_CNT\":2,\"ROUTE_DEP_TM\":\"0815\",\"RUN_CD\":\"1\",\"TRANSP_BIZR_ID\":\"6300012\",\"GROUP_DC_CNT\":0,\"TOT_SEAT_CNT\":\"00\",\"FARE_DC_AMT\":0,\"RESERVATION_CHK\":\"1\",\"BUS_TYPE\":\"1\",\"FARE1\":0,\"FARE0\":3200,\"FARE3\":1600,\"FARE2\":2600},{\"eterCode\":\"7009\",\"DATE_ARRAY\":\"2025-06-22 (일),2025-06-23 (월),2025-06-24 (화),2025-06-25 (수),2025-06-26 (목),2025-06-27 (금),2025-06-28 (토),2025-06-29 (일)\",\"DEP_DATE\":\"20250624\",\"BUS_ORDER_CREATE_DAYS\":7,\"REMAIN_CNT\":\"00\",\"DIST_TIME\":0,\"OPENGBN\":\"2\",\"ARR_CD\":\"1\",\"MOBILE_TICKET_CD\":\"0\",\"ROUTE_DATA\":\"효자동→김제→부안\",\"FARE_DC_CD\":\"0\",\"BUS_TYPE_NM\":\"일반\",\"TRANSP_BIZR_ABBR_NM\":\"㈜전주고속\",\"RESERVE_SEAT_CNT\":0,\"BUS_ROUTE_ID\":\"707341701801\",\"DIV_CD\":\"1\",\"DEP_TIME\":\"0840\",\"sterCode\":\"7341\",\"DISTANCE\":0,\"BLANK_CNT\":\"00\",\"GUBUN_CD\":\"EBC\",\"BUS_ORDER_DT\":\"20250624\",\"RESERVE_DC_CNT\":0,\"STATION_TOT_CNT\":2,\"ROUTE_DEP_TM\":\"0840\",\"RUN_CD\":\"1\",\"TRANSP_BIZR_ID\":\"6300012\",\"GROUP_DC_CNT\":0,\"TOT_SEAT_CNT\":\"00\",\"FARE_DC_AMT\":0,\"RESERVATION_CHK\":\"1\",\"BUS_TYPE\":\"1\",\"FARE1\":0,\"FARE0\":3200,\"FARE3\":1600,\"FARE2\":2600},{\"eterCode\":\"7009\",\"DATE_ARRAY\":\"2025-06-22 (일),2025-06-23 (월),2025-06-24 (화),2025-06-25 (수),2025-06-26 (목),2025-06-27 (금),2025-06-28 (토),2025-06-29 (일)\",\"DEP_DATE\":\"20250624\",\"BUS_ORDER_CREATE_DAYS\":7,\"REMAIN_CNT\":\"00\",\"DIST_TIME\":0,\"OPENGBN\":\"2\",\"ARR_CD\":\"1\",\"MOBILE_TICKET_CD\":\"0\",\"ROUTE_DATA\":\"효자동→김제\",\"FARE_DC_CD\":\"0\",\"BUS_TYPE_NM\":\"일반\",\"TRANSP_BIZR_ABBR_NM\":\"전북여객(주)\",\"RESERVE_SEAT_CNT\":0,\"BUS_ROUTE_ID\":\"707341700901\",\"DIV_CD\":\"1\",\"DEP_TIME\":\"0849\",\"sterCode\":\"7341\",\"DISTANCE\":0,\"BLANK_CNT\":\"00\",\"GUBUN_CD\":\"EBC\",\"BUS_ORDER_DT\":\"20250624\",\"RESERVE_DC_CNT\":0,\"STATION_TOT_CNT\":2,\"ROUTE_DEP_TM\":\"0849\",\"RUN_CD\":\"1\",\"TRANSP_BIZR_ID\":\"6300016\",\"GROUP_DC_CNT\":0,\"TOT_SEAT_CNT\":\"00\",\"FARE_DC_AMT\":0,\"RESERVATION_CHK\":\"1\",\"BUS_TYPE\":\"1\",\"FARE1\":0,\"FARE0\":3200,\"FARE3\":1600,\"FARE2\":2600},{\"eterCode\":\"7009\",\"DATE_ARRAY\":\"2025-06-22 (일),2025-06-23 (월),2025-06-24 (화),2025-06-25 (수),2025-06-26 (목),2025-06-27 (금),2025-06-28 (토),2025-06-29 (일)\",\"DEP_DATE\":\"20250624\",\"BUS_ORDER_CREATE_DAYS\":7,\"REMAIN_CNT\":\"00\",\"DIST_TIME\":0,\"OPENGBN\":\"2\",\"ARR_CD\":\"1\",\"MOBILE_TICKET_CD\":\"0\",\"ROUTE_DATA\":\"효자동→김제→부안→곰소→내소사\",\"FARE_DC_CD\":\"0\",\"BUS_TYPE_NM\":\"일반\",\"TRANSP_BIZR_ABBR_NM\":\"㈜전주고속\",\"RESERVE_SEAT_CNT\":0,\"BUS_ROUTE_ID\":\"707341707701\",\"DIV_CD\":\"1\",\"DEP_TIME\":\"0910\",\"sterCode\":\"7341\",\"DISTANCE\":0,\"BLANK_CNT\":\"00\",\"GUBUN_CD\":\"EBC\",\"BUS_ORDER_DT\":\"20250624\",\"RESERVE_DC_CNT\":0,\"STATION_TOT_CNT\":2,\"ROUTE_DEP_TM\":\"0910\",\"RUN_CD\":\"1\",\"TRANSP_BIZR_ID\":\"6300012\",\"GROUP_DC_CNT\":0,\"TOT_SEAT_CNT\":\"00\",\"FARE_DC_AMT\":0,\"RESERVATION_CHK\":\"1\",\"BUS_TYPE\":\"1\",\"FARE1\":0,\"FARE0\":3200,\"FARE3\":1600,\"FARE2\":2600},{\"eterCode\":\"7009\",\"DATE_ARRAY\":\"2025-06-22 (일),2025-06-23 (월),2025-06-24 (화),2025-06-25 (수),2025-06-26 (목),2025-06-27 (금),2025-06-28 (토),2025-06-29 (일)\",\"DEP_DATE\":\"20250624\",\"BUS_ORDER_CREATE_DAYS\":7,\"REMAIN_CNT\":\"00\",\"DIST_TIME\":0,\"OPENGBN\":\"2\",\"ARR_CD\":\"1\",\"MOBILE_TICKET_CD\":\"0\",\"ROUTE_DATA\":\"효자동→김제→부안\",\"FARE_DC_CD\":\"0\",\"BUS_TYPE_NM\":\"일반\",\"TRANSP_BIZR_ABBR_NM\":\"㈜전북고속\",\"RESERVE_SEAT_CNT\":0,\"BUS_ROUTE_ID\":\"707341701801\",\"DIV_CD\":\"1\",\"DEP_TIME\":\"0930\",\"sterCode\":\"7341\",\"DISTANCE\":0,\"BLANK_CNT\":\"00\",\"GUBUN_CD\":\"EBC\",\"BUS_ORDER_DT\":\"20250624\",\"RESERVE_DC_CNT\":0,\"STATION_TOT_CNT\":2,\"ROUTE_DEP_TM\":\"0930\",\"RUN_CD\":\"1\",\"TRANSP_BIZR_ID\":\"6300011\",\"GROUP_DC_CNT\":0,\"TOT_SEAT_CNT\":\"00\",\"FARE_DC_AMT\":0,\"RESERVATION_CHK\":\"1\",\"BUS_TYPE\":\"1\",\"FARE1\":0,\"FARE0\":3200,\"FARE3\":1600,\"FARE2\":2600},{\"eterCode\":\"7009\",\"DATE_ARRAY\":\"2025-06-22 (일),2025-06-23 (월),2025-06-24 (화),2025-06-25 (수),2025-06-26 (목),2025-06-27 (금),2025-06-28 (토),2025-06-29 (일)\",\"DEP_DATE\":\"20250624\",\"BUS_ORDER_CREATE_DAYS\":7,\"REMAIN_CNT\":\"00\",\"DIST_TIME\":0,\"OPENGBN\":\"2\",\"ARR_CD\":\"1\",\"MOBILE_TICKET_CD\":\"0\",\"ROUTE_DATA\":\"효자동→김제→부안→변산욕장→변산→격포\",\"FARE_DC_CD\":\"0\",\"BUS_TYPE_NM\":\"일반\",\"TRANSP_BIZR_ABBR_NM\":\"전북여객(주)\",\"RESERVE_SEAT_CNT\":0,\"BUS_ROUTE_ID\":\"707341813701\",\"DIV_CD\":\"1\",\"DEP_TIME\":\"0930\",\"sterCode\":\"7341\",\"DISTANCE\":0,\"BLANK_CNT\":\"00\",\"GUBUN_CD\":\"EBC\",\"BUS_ORDER_DT\":\"20250624\",\"RESERVE_DC_CNT\":0,\"STATION_TOT_CNT\":2,\"ROUTE_DEP_TM\":\"0930\",\"RUN_CD\":\"1\",\"TRANSP_BIZR_ID\":\"6300016\",\"GROUP_DC_CNT\":0,\"TOT_SEAT_CNT\":\"00\",\"FARE_DC_AMT\":0,\"RESERVATION_CHK\":\"1\",\"BUS_TYPE\":\"1\",\"FARE1\":0,\"FARE0\":3200,\"FARE3\":1600,\"FARE2\":2600},{\"eterCode\":\"7009\",\"DATE_ARRAY\":\"2025-06-22 (일),2025-06-23 (월),2025-06-24 (화),2025-06-25 (수),2025-06-26 (목),2025-06-27 (금),2025-06-28 (토),2025-06-29 (일)\",\"DEP_DATE\":\"20250624\",\"BUS_ORDER_CREATE_DAYS\":7,\"REMAIN_CNT\":\"00\",\"DIST_TIME\":0,\"OPENGBN\":\"2\",\"ARR_CD\":\"1\",\"MOBILE_TICKET_CD\":\"0\",\"ROUTE_DATA\":\"효자동→김제→부안\",\"FARE_DC_CD\":\"0\",\"BUS_TYPE_NM\":\"일반\",\"TRANSP_BIZR_ABBR_NM\":\"㈜전주고속\",\"RESERVE_SEAT_CNT\":0,\"BUS_ROUTE_ID\":\"707341701801\",\"DIV_CD\":\"1\",\"DEP_TIME\":\"1015\",\"sterCode\":\"7341\",\"DISTANCE\":0,\"BLANK_CNT\":\"00\",\"GUBUN_CD\":\"EBC\",\"BUS_ORDER_DT\":\"20250624\",\"RESERVE_DC_CNT\":0,\"STATION_TOT_CNT\":2,\"ROUTE_DEP_TM\":\"1015\",\"RUN_CD\":\"1\",\"TRANSP_BIZR_ID\":\"6300012\",\"GROUP_DC_CNT\":0,\"TOT_SEAT_CNT\":\"00\",\"FARE_DC_AMT\":0,\"RESERVATION_CHK\":\"1\",\"BUS_TYPE\":\"1\",\"FARE1\":0,\"FARE0\":3200,\"FARE3\":1600,\"FARE2\":2600},{\"eterCode\":\"7009\",\"DATE_ARRAY\":\"2025-06-22 (일),2025-06-23 (월),2025-06-24 (화),2025-06-25 (수),2025-06-26 (목),2025-06-27 (금),2025-06-28 (토),2025-06-29 (일)\",\"DEP_DATE\":\"20250624\",\"BUS_ORDER_CREATE_DAYS\":7,\"REMAIN_CNT\":\"00\",\"DIST_TIME\":0,\"OPENGBN\":\"2\",\"ARR_CD\":\"1\",\"MOBILE_TICKET_CD\":\"0\",\"ROUTE_DATA\":\"효자동→김제\",\"FARE_DC_CD\":\"0\",\"BUS_TYPE_NM\":\"일반\",\"TRANSP_BIZR_ABBR_NM\":\"전북여객(주)\",\"RESERVE_SEAT_CNT\":0,\"BUS_ROUTE_ID\":\"707341700901\",\"DIV_CD\":\"1\",\"DEP_TIME\":\"1039\",\"sterCode\":\"7341\",\"DISTANCE\":0,\"BLANK_CNT\":\"00\",\"GUBUN_CD\":\"EBC\",\"BUS_ORDER_DT\":\"20250624\",\"RESERVE_DC_CNT\":0,\"STATION_TOT_CNT\":2,\"ROUTE_DEP_TM\":\"1039\",\"RUN_CD\":\"1\",\"TRANSP_BIZR_ID\":\"6300016\",\"GROUP_DC_CNT\":0,\"TOT_SEAT_CNT\":\"00\",\"FARE_DC_AMT\":0,\"RESERVATION_CHK\":\"1\",\"BUS_TYPE\":\"1\",\"FARE1\":0,\"FARE0\":3200,\"FARE3\":1600,\"FARE2\":2600},{\"eterCode\":\"7009\",\"DATE_ARRAY\":\"2025-06-22 (일),2025-06-23 (월),2025-06-24 (화),2025-06-25 (수),2025-06-26 (목),2025-06-27 (금),2025-06-28 (토),2025-06-29 (일)\",\"DEP_DATE\":\"20250624\",\"BUS_ORDER_CREATE_DAYS\":7,\"REMAIN_CNT\":\"00\",\"DIST_TIME\":0,\"OPENGBN\":\"2\",\"ARR_CD\":\"1\",\"MOBILE_TICKET_CD\":\"0\",\"ROUTE_DATA\":\"효자동→김제→부안\",\"FARE_DC_CD\":\"0\",\"BUS_TYPE_NM\":\"일반\",\"TRANSP_BIZR_ABBR_NM\":\"㈜전북고속\",\"RESERVE_SEAT_CNT\":0,\"BUS_ROUTE_ID\":\"707341701801\",\"DIV_CD\":\"1\",\"DEP_TIME\":\"1055\",\"sterCode\":\"7341\",\"DISTANCE\":0,\"BLANK_CNT\":\"00\",\"GUBUN_CD\":\"EBC\",\"BUS_ORDER_DT\":\"20250624\",\"RESERVE_DC_CNT\":0,\"STATION_TOT_CNT\":2,\"ROUTE_DEP_TM\":\"1055\",\"RUN_CD\":\"1\",\"TRANSP_BIZR_ID\":\"6300011\",\"GROUP_DC_CNT\":0,\"TOT_SEAT_CNT\":\"00\",\"FARE_DC_AMT\":0,\"RESERVATION_CHK\":\"1\",\"BUS_TYPE\":\"1\",\"FARE1\":0,\"FARE0\":3200,\"FARE3\":1600,\"FARE2\":2600},{\"eterCode\":\"7009\",\"DATE_ARRAY\":\"2025-06-22 (일),2025-06-23 (월),2025-06-24 (화),2025-06-25 (수),2025-06-26 (목),2025-06-27 (금),2025-06-28 (토),2025-06-29 (일)\",\"DEP_DATE\":\"20250624\",\"BUS_ORDER_CREATE_DAYS\":7,\"REMAIN_CNT\":\"00\",\"DIST_TIME\":0,\"OPENGBN\":\"2\",\"ARR_CD\":\"1\",\"MOBILE_TICKET_CD\":\"0\",\"ROUTE_DATA\":\"효자동→김제\",\"FARE_DC_CD\":\"0\",\"BUS_TYPE_NM\":\"일반\",\"TRANSP_BIZR_ABBR_NM\":\"전북여객(주)\",\"RESERVE_SEAT_CNT\":0,\"BUS_ROUTE_ID\":\"707341700901\",\"DIV_CD\":\"1\",\"DEP_TIME\":\"1104\",\"sterCode\":\"7341\",\"DISTANCE\":0,\"BLANK_CNT\":\"00\",\"GUBUN_CD\":\"EBC\",\"BUS_ORDER_DT\":\"20250624\",\"RESERVE_DC_CNT\":0,\"STATION_TOT_CNT\":2,\"ROUTE_DEP_TM\":\"1104\",\"RUN_CD\":\"1\",\"TRANSP_BIZR_ID\":\"6300016\",\"GROUP_DC_CNT\":0,\"TOT_SEAT_CNT\":\"00\",\"FARE_DC_AMT\":0,\"RESERVATION_CHK\":\"1\",\"BUS_TYPE\":\"1\",\"FARE1\":0,\"FARE0\":3200,\"FARE3\":1600,\"FARE2\":2600},{\"eterCode\":\"7009\",\"DATE_ARRAY\":\"2025-06-22 (일),2025-06-23 (월),2025-06-24 (화),2025-06-25 (수),2025-06-26 (목),2025-06-27 (금),2025-06-28 (토),2025-06-29 (일)\",\"DEP_DATE\":\"20250624\",\"BUS_ORDER_CREATE_DAYS\":7,\"REMAIN_CNT\":\"00\",\"DIST_TIME\":0,\"OPENGBN\":\"2\",\"ARR_CD\":\"1\",\"MOBILE_TICKET_CD\":\"0\",\"ROUTE_DATA\":\"효자동→김제→부안\",\"FARE_DC_CD\":\"0\",\"BUS_TYPE_NM\":\"일반\",\"TRANSP_BIZR_ABBR_NM\":\"㈜전북고속\",\"RESERVE_SEAT_CNT\":0,\"BUS_ROUTE_ID\":\"707341701801\",\"DIV_CD\":\"1\",\"DEP_TIME\":\"1130\",\"sterCode\":\"7341\",\"DISTANCE\":0,\"BLANK_CNT\":\"00\",\"GUBUN_CD\":\"EBC\",\"BUS_ORDER_DT\":\"20250624\",\"RESERVE_DC_CNT\":0,\"STATION_TOT_CNT\":2,\"ROUTE_DEP_TM\":\"1130\",\"RUN_CD\":\"1\",\"TRANSP_BIZR_ID\":\"6300011\",\"GROUP_DC_CNT\":0,\"TOT_SEAT_CNT\":\"00\",\"FARE_DC_AMT\":0,\"RESERVATION_CHK\":\"1\",\"BUS_TYPE\":\"1\",\"FARE1\":0,\"FARE0\":3200,\"FARE3\":1600,\"FARE2\":2600},{\"eterCode\":\"7009\",\"DATE_ARRAY\":\"2025-06-22 (일),2025-06-23 (월),2025-06-24 (화),2025-06-25 (수),2025-06-26 (목),2025-06-27 (금),2025-06-28 (토),2025-06-29 (일)\",\"DEP_DATE\":\"20250624\",\"BUS_ORDER_CREATE_DAYS\":7,\"REMAIN_CNT\":\"00\",\"DIST_TIME\":0,\"OPENGBN\":\"2\",\"ARR_CD\":\"1\",\"MOBILE_TICKET_CD\":\"0\",\"ROUTE_DATA\":\"효자동→김제\",\"FARE_DC_CD\":\"0\",\"BUS_TYPE_NM\":\"일반\",\"TRANSP_BIZR_ABBR_NM\":\"전북여객(주)\",\"RESERVE_SEAT_CNT\":0,\"BUS_ROUTE_ID\":\"707341700901\",\"DIV_CD\":\"1\",\"DEP_TIME\":\"1139\",\"sterCode\":\"7341\",\"DISTANCE\":0,\"BLANK_CNT\":\"00\",\"GUBUN_CD\":\"EBC\",\"BUS_ORDER_DT\":\"20250624\",\"RESERVE_DC_CNT\":0,\"STATION_TOT_CNT\":2,\"ROUTE_DEP_TM\":\"1139\",\"RUN_CD\":\"1\",\"TRANSP_BIZR_ID\":\"6300016\",\"GROUP_DC_CNT\":0,\"TOT_SEAT_CNT\":\"00\",\"FARE_DC_AMT\":0,\"RESERVATION_CHK\":\"1\",\"BUS_TYPE\":\"1\",\"FARE1\":0,\"FARE0\":3200,\"FARE3\":1600,\"FARE2\":2600},{\"eterCode\":\"7009\",\"DATE_ARRAY\":\"2025-06-22 (일),2025-06-23 (월),2025-06-24 (화),2025-06-25 (수),2025-06-26 (목),2025-06-27 (금),2025-06-28 (토),2025-06-29 (일)\",\"DEP_DATE\":\"20250624\",\"BUS_ORDER_CREATE_DAYS\":7,\"REMAIN_CNT\":\"00\",\"DIST_TIME\":0,\"OPENGBN\":\"2\",\"ARR_CD\":\"1\",\"MOBILE_TICKET_CD\":\"0\",\"ROUTE_DATA\":\"효자동→김제→부안\",\"FARE_DC_CD\":\"0\",\"BUS_TYPE_NM\":\"일반\",\"TRANSP_BIZR_ABBR_NM\":\"㈜전주고속\",\"RESERVE_SEAT_CNT\":0,\"BUS_ROUTE_ID\":\"707341701801\",\"DIV_CD\":\"1\",\"DEP_TIME\":\"1155\",\"sterCode\":\"7341\",\"DISTANCE\":0,\"BLANK_CNT\":\"00\",\"GUBUN_CD\":\"EBC\",\"BUS_ORDER_DT\":\"20250624\",\"RESERVE_DC_CNT\":0,\"STATION_TOT_CNT\":2,\"ROUTE_DEP_TM\":\"1155\",\"RUN_CD\":\"1\",\"TRANSP_BIZR_ID\":\"6300012\",\"GROUP_DC_CNT\":0,\"TOT_SEAT_CNT\":\"00\",\"FARE_DC_AMT\":0,\"RESERVATION_CHK\":\"1\",\"BUS_TYPE\":\"1\",\"FARE1\":0,\"FARE0\":3200,\"FARE3\":1600,\"FARE2\":2600},{\"eterCode\":\"7009\",\"DATE_ARRAY\":\"2025-06-22 (일),2025-06-23 (월),2025-06-24 (화),2025-06-25 (수),2025-06-26 (목),2025-06-27 (금),2025-06-28 (토),2025-06-29 (일)\",\"DEP_DATE\":\"20250624\",\"BUS_ORDER_CREATE_DAYS\":7,\"REMAIN_CNT\":\"00\",\"DIST_TIME\":0,\"OPENGBN\":\"2\",\"ARR_CD\":\"1\",\"MOBILE_TICKET_CD\":\"0\",\"ROUTE_DATA\":\"효자동→김제\",\"FARE_DC_CD\":\"0\",\"BUS_TYPE_NM\":\"일반\",\"TRANSP_BIZR_ABBR_NM\":\"전북여객(주)\",\"RESERVE_SEAT_CNT\":0,\"BUS_ROUTE_ID\":\"707341700901\",\"DIV_CD\":\"1\",\"DEP_TIME\":\"1239\",\"sterCode\":\"7341\",\"DISTANCE\":0,\"BLANK_CNT\":\"00\",\"GUBUN_CD\":\"EBC\",\"BUS_ORDER_DT\":\"20250624\",\"RESERVE_DC_CNT\":0,\"STATION_TOT_CNT\":2,\"ROUTE_DEP_TM\":\"1239\",\"RUN_CD\":\"1\",\"TRANSP_BIZR_ID\":\"6300016\",\"GROUP_DC_CNT\":0,\"TOT_SEAT_CNT\":\"00\",\"FARE_DC_AMT\":0,\"RESERVATION_CHK\":\"1\",\"BUS_TYPE\":\"1\",\"FARE1\":0,\"FARE0\":3200,\"FARE3\":1600,\"FARE2\":2600},{\"eterCode\":\"7009\",\"DATE_ARRAY\":\"2025-06-22 (일),2025-06-23 (월),2025-06-24 (화),2025-06-25 (수),2025-06-26 (목),2025-06-27 (금),2025-06-28 (토),2025-06-29 (일)\",\"DEP_DATE\":\"20250624\",\"BUS_ORDER_CREATE_DAYS\":7,\"REMAIN_CNT\":\"00\",\"DIST_TIME\":0,\"OPENGBN\":\"2\",\"ARR_CD\":\"1\",\"MOBILE_TICKET_CD\":\"0\",\"ROUTE_DATA\":\"효자동→김제→부안\",\"FARE_DC_CD\":\"0\",\"BUS_TYPE_NM\":\"일반\",\"TRANSP_BIZR_ABBR_NM\":\"㈜전북고속\",\"RESERVE_SEAT_CNT\":0,\"BUS_ROUTE_ID\":\"707341701801\",\"DIV_CD\":\"1\",\"DEP_TIME\":\"1245\",\"sterCode\":\"7341\",\"DISTANCE\":0,\"BLANK_CNT\":\"00\",\"GUBUN_CD\":\"EBC\",\"BUS_ORDER_DT\":\"20250624\",\"RESERVE_DC_CNT\":0,\"STATION_TOT_CNT\":2,\"ROUTE_DEP_TM\":\"1245\",\"RUN_CD\":\"1\",\"TRANSP_BIZR_ID\":\"6300011\",\"GROUP_DC_CNT\":0,\"TOT_SEAT_CNT\":\"00\",\"FARE_DC_AMT\":0,\"RESERVATION_CHK\":\"1\",\"BUS_TYPE\":\"1\",\"FARE1\":0,\"FARE0\":3200,\"FARE3\":1600,\"FARE2\":2600},{\"eterCode\":\"7009\",\"DATE_ARRAY\":\"2025-06-22 (일),2025-06-23 (월),2025-06-24 (화),2025-06-25 (수),2025-06-26 (목),2025-06-27 (금),2025-06-28 (토),2025-06-29 (일)\",\"DEP_DATE\":\"20250624\",\"BUS_ORDER_CREATE_DAYS\":7,\"REMAIN_CNT\":\"00\",\"DIST_TIME\":0,\"OPENGBN\":\"2\",\"ARR_CD\":\"1\",\"MOBILE_TICKET_CD\":\"0\",\"ROUTE_DATA\":\"효자동→김제\",\"FARE_DC_CD\":\"0\",\"BUS_TYPE_NM\":\"일반\",\"TRANSP_BIZR_ABBR_NM\":\"전북여객(주)\",\"RESERVE_SEAT_CNT\":0,\"BUS_ROUTE_ID\":\"707341700901\",\"DIV_CD\":\"1\",\"DEP_TIME\":\"1254\",\"sterCode\":\"7341\",\"DISTANCE\":0,\"BLANK_CNT\":\"00\",\"GUBUN_CD\":\"EBC\",\"BUS_ORDER_DT\":\"20250624\",\"RESERVE_DC_CNT\":0,\"STATION_TOT_CNT\":2,\"ROUTE_DEP_TM\":\"1254\",\"RUN_CD\":\"1\",\"TRANSP_BIZR_ID\":\"6300016\",\"GROUP_DC_CNT\":0,\"TOT_SEAT_CNT\":\"00\",\"FARE_DC_AMT\":0,\"RESERVATION_CHK\":\"1\",\"BUS_TYPE\":\"1\",\"FARE1\":0,\"FARE0\":3200,\"FARE3\":1600,\"FARE2\":2600},{\"eterCode\":\"7009\",\"DATE_ARRAY\":\"2025-06-22 (일),2025-06-23 (월),2025-06-24 (화),2025-06-25 (수),2025-06-26 (목),2025-06-27 (금),2025-06-28 (토),2025-06-29 (일)\",\"DEP_DATE\":\"20250624\",\"BUS_ORDER_CREATE_DAYS\":7,\"REMAIN_CNT\":\"00\",\"DIST_TIME\":0,\"OPENGBN\":\"2\",\"ARR_CD\":\"1\",\"MOBILE_TICKET_CD\":\"0\",\"ROUTE_DATA\":\"효자동→김제\",\"FARE_DC_CD\":\"0\",\"BUS_TYPE_NM\":\"일반\",\"TRANSP_BIZR_ABBR_NM\":\"전북여객(주)\",\"RESERVE_SEAT_CNT\":0,\"BUS_ROUTE_ID\":\"707341700901\",\"DIV_CD\":\"1\",\"DEP_TIME\":\"1324\",\"sterCode\":\"7341\",\"DISTANCE\":0,\"BLANK_CNT\":\"00\",\"GUBUN_CD\":\"EBC\",\"BUS_ORDER_DT\":\"20250624\",\"RESERVE_DC_CNT\":0,\"STATION_TOT_CNT\":2,\"ROUTE_DEP_TM\":\"1324\",\"RUN_CD\":\"1\",\"TRANSP_BIZR_ID\":\"6300016\",\"GROUP_DC_CNT\":0,\"TOT_SEAT_CNT\":\"00\",\"FARE_DC_AMT\":0,\"RESERVATION_CHK\":\"1\",\"BUS_TYPE\":\"1\",\"FARE1\":0,\"FARE0\":3200,\"FARE3\":1600,\"FARE2\":2600},{\"eterCode\":\"7009\",\"DATE_ARRAY\":\"2025-06-22 (일),2025-06-23 (월),2025-06-24 (화),2025-06-25 (수),2025-06-26 (목),2025-06-27 (금),2025-06-28 (토),2025-06-29 (일)\",\"DEP_DATE\":\"20250624\",\"BUS_ORDER_CREATE_DAYS\":7,\"REMAIN_CNT\":\"00\",\"DIST_TIME\":0,\"OPENGBN\":\"2\",\"ARR_CD\":\"1\",\"MOBILE_TICKET_CD\":\"0\",\"ROUTE_DATA\":\"효자동→김제→부안→변산욕장→변산→격포\",\"FARE_DC_CD\":\"0\",\"BUS_TYPE_NM\":\"일반\",\"TRANSP_BIZR_ABBR_NM\":\"㈜전주고속\",\"RESERVE_SEAT_CNT\":0,\"BUS_ROUTE_ID\":\"707341813701\",\"DIV_CD\":\"1\",\"DEP_TIME\":\"1330\",\"sterCode\":\"7341\",\"DISTANCE\":0,\"BLANK_CNT\":\"00\",\"GUBUN_CD\":\"EBC\",\"BUS_ORDER_DT\":\"20250624\",\"RESERVE_DC_CNT\":0,\"STATION_TOT_CNT\":2,\"ROUTE_DEP_TM\":\"1330\",\"RUN_CD\":\"1\",\"TRANSP_BIZR_ID\":\"6300012\",\"GROUP_DC_CNT\":0,\"TOT_SEAT_CNT\":\"00\",\"FARE_DC_AMT\":0,\"RESERVATION_CHK\":\"1\",\"BUS_TYPE\":\"1\",\"FARE1\":0,\"FARE0\":3200,\"FARE3\":1600,\"FARE2\":2600},{\"eterCode\":\"7009\",\"DATE_ARRAY\":\"2025-06-22 (일),2025-06-23 (월),2025-06-24 (화),2025-06-25 (수),2025-06-26 (목),2025-06-27 (금),2025-06-28 (토),2025-06-29 (일)\",\"DEP_DATE\":\"20250624\",\"BUS_ORDER_CREATE_DAYS\":7,\"REMAIN_CNT\":\"00\",\"DIST_TIME\":0,\"OPENGBN\":\"2\",\"ARR_CD\":\"1\",\"MOBILE_TICKET_CD\":\"0\",\"ROUTE_DATA\":\"효자동→김제→부안\",\"FARE_DC_CD\":\"0\",\"BUS_TYPE_NM\":\"일반\",\"TRANSP_BIZR_ABBR_NM\":\"㈜전북고속\",\"RESERVE_SEAT_CNT\":0,\"BUS_ROUTE_ID\":\"707341701801\",\"DIV_CD\":\"1\",\"DEP_TIME\":\"1355\",\"sterCode\":\"7341\",\"DISTANCE\":0,\"BLANK_CNT\":\"00\",\"GUBUN_CD\":\"EBC\",\"BUS_ORDER_DT\":\"20250624\",\"RESERVE_DC_CNT\":0,\"STATION_TOT_CNT\":2,\"ROUTE_DEP_TM\":\"1355\",\"RUN_CD\":\"1\",\"TRANSP_BIZR_ID\":\"6300011\",\"GROUP_DC_CNT\":0,\"TOT_SEAT_CNT\":\"00\",\"FARE_DC_AMT\":0,\"RESERVATION_CHK\":\"1\",\"BUS_TYPE\":\"1\",\"FARE1\":0,\"FARE0\":3200,\"FARE3\":1600,\"FARE2\":2600},{\"eterCode\":\"7009\",\"DATE_ARRAY\":\"2025-06-22 (일),2025-06-23 (월),2025-06-24 (화),2025-06-25 (수),2025-06-26 (목),2025-06-27 (금),2025-06-28 (토),2025-06-29 (일)\",\"DEP_DATE\":\"20250624\",\"BUS_ORDER_CREATE_DAYS\":7,\"REMAIN_CNT\":\"00\",\"DIST_TIME\":0,\"OPENGBN\":\"2\",\"ARR_CD\":\"1\",\"MOBILE_TICKET_CD\":\"0\",\"ROUTE_DATA\":\"효자동→김제\",\"FARE_DC_CD\":\"0\",\"BUS_TYPE_NM\":\"일반\",\"TRANSP_BIZR_ABBR_NM\":\"전북여객(주)\",\"RESERVE_SEAT_CNT\":0,\"BUS_ROUTE_ID\":\"707341700901\",\"DIV_CD\":\"1\",\"DEP_TIME\":\"1424\",\"sterCode\":\"7341\",\"DISTANCE\":0,\"BLANK_CNT\":\"00\",\"GUBUN_CD\":\"EBC\",\"BUS_ORDER_DT\":\"20250624\",\"RESERVE_DC_CNT\":0,\"STATION_TOT_CNT\":2,\"ROUTE_DEP_TM\":\"1424\",\"RUN_CD\":\"1\",\"TRANSP_BIZR_ID\":\"6300016\",\"GROUP_DC_CNT\":0,\"TOT_SEAT_CNT\":\"00\",\"FARE_DC_AMT\":0,\"RESERVATION_CHK\":\"1\",\"BUS_TYPE\":\"1\",\"FARE1\":0,\"FARE0\":3200,\"FARE3\":1600,\"FARE2\":2600},{\"eterCode\":\"7009\",\"DATE_ARRAY\":\"2025-06-22 (일),2025-06-23 (월),2025-06-24 (화),2025-06-25 (수),2025-06-26 (목),2025-06-27 (금),2025-06-28 (토),2025-06-29 (일)\",\"DEP_DATE\":\"20250624\",\"BUS_ORDER_CREATE_DAYS\":7,\"REMAIN_CNT\":\"00\",\"DIST_TIME\":0,\"OPENGBN\":\"2\",\"ARR_CD\":\"1\",\"MOBILE_TICKET_CD\":\"0\",\"ROUTE_DATA\":\"효자동→김제→부안\",\"FARE_DC_CD\":\"0\",\"BUS_TYPE_NM\":\"일반\",\"TRANSP_BIZR_ABBR_NM\":\"㈜전주고속\",\"RESERVE_SEAT_CNT\":0,\"BUS_ROUTE_ID\":\"707341701801\",\"DIV_CD\":\"1\",\"DEP_TIME\":\"1440\",\"sterCode\":\"7341\",\"DISTANCE\":0,\"BLANK_CNT\":\"00\",\"GUBUN_CD\":\"EBC\",\"BUS_ORDER_DT\":\"20250624\",\"RESERVE_DC_CNT\":0,\"STATION_TOT_CNT\":2,\"ROUTE_DEP_TM\":\"1440\",\"RUN_CD\":\"1\",\"TRANSP_BIZR_ID\":\"6300012\",\"GROUP_DC_CNT\":0,\"TOT_SEAT_CNT\":\"00\",\"FARE_DC_AMT\":0,\"RESERVATION_CHK\":\"1\",\"BUS_TYPE\":\"1\",\"FARE1\":0,\"FARE0\":3200,\"FARE3\":1600,\"FARE2\":2600},{\"eterCode\":\"7009\",\"DATE_ARRAY\":\"2025-06-22 (일),2025-06-23 (월),2025-06-24 (화),2025-06-25 (수),2025-06-26 (목),2025-06-27 (금),2025-06-28 (토),2025-06-29 (일)\",\"DEP_DATE\":\"20250624\",\"BUS_ORDER_CREATE_DAYS\":7,\"REMAIN_CNT\":\"00\",\"DIST_TIME\":0,\"OPENGBN\":\"2\",\"ARR_CD\":\"1\",\"MOBILE_TICKET_CD\":\"0\",\"ROUTE_DATA\":\"효자동→김제\",\"FARE_DC_CD\":\"0\",\"BUS_TYPE_NM\":\"일반\",\"TRANSP_BIZR_ABBR_NM\":\"전북여객(주)\",\"RESERVE_SEAT_CNT\":0,\"BUS_ROUTE_ID\":\"707341700901\",\"DIV_CD\":\"1\",\"DEP_TIME\":\"1449\",\"sterCode\":\"7341\",\"DISTANCE\":0,\"BLANK_CNT\":\"00\",\"GUBUN_CD\":\"EBC\",\"BUS_ORDER_DT\":\"20250624\",\"RESERVE_DC_CNT\":0,\"STATION_TOT_CNT\":2,\"ROUTE_DEP_TM\":\"1449\",\"RUN_CD\":\"1\",\"TRANSP_BIZR_ID\":\"6300016\",\"GROUP_DC_CNT\":0,\"TOT_SEAT_CNT\":\"00\",\"FARE_DC_AMT\":0,\"RESERVATION_CHK\":\"1\",\"BUS_TYPE\":\"1\",\"FARE1\":0,\"FARE0\":3200,\"FARE3\":1600,\"FARE2\":2600},{\"eterCode\":\"7009\",\"DATE_ARRAY\":\"2025-06-22 (일),2025-06-23 (월),2025-06-24 (화),2025-06-25 (수),2025-06-26 (목),2025-06-27 (금),2025-06-28 (토),2025-06-29 (일)\",\"DEP_DATE\":\"20250624\",\"BUS_ORDER_CREATE_DAYS\":7,\"REMAIN_CNT\":\"00\",\"DIST_TIME\":0,\"OPENGBN\":\"2\",\"ARR_CD\":\"1\",\"MOBILE_TICKET_CD\":\"0\",\"ROUTE_DATA\":\"효자동→김제\",\"FARE_DC_CD\":\"0\",\"BUS_TYPE_NM\":\"일반\",\"TRANSP_BIZR_ABBR_NM\":\"㈜전주고속\",\"RESERVE_SEAT_CNT\":0,\"BUS_ROUTE_ID\":\"707341700901\",\"DIV_CD\":\"1\",\"DEP_TIME\":\"1500\",\"sterCode\":\"7341\",\"DISTANCE\":0,\"BLANK_CNT\":\"00\",\"GUBUN_CD\":\"EBC\",\"BUS_ORDER_DT\":\"20250624\",\"RESERVE_DC_CNT\":0,\"STATION_TOT_CNT\":2,\"ROUTE_DEP_TM\":\"1500\",\"RUN_CD\":\"1\",\"TRANSP_BIZR_ID\":\"6300012\",\"GROUP_DC_CNT\":0,\"TOT_SEAT_CNT\":\"00\",\"FARE_DC_AMT\":0,\"RESERVATION_CHK\":\"1\",\"BUS_TYPE\":\"1\",\"FARE1\":0,\"FARE0\":3200,\"FARE3\":1600,\"FARE2\":2600},{\"eterCode\":\"7009\",\"DATE_ARRAY\":\"2025-06-22 (일),2025-06-23 (월),2025-06-24 (화),2025-06-25 (수),2025-06-26 (목),2025-06-27 (금),2025-06-28 (토),2025-06-29 (일)\",\"DEP_DATE\":\"20250624\",\"BUS_ORDER_CREATE_DAYS\":7,\"REMAIN_CNT\":\"00\",\"DIST_TIME\":0,\"OPENGBN\":\"2\",\"ARR_CD\":\"1\",\"MOBILE_TICKET_CD\":\"0\",\"ROUTE_DATA\":\"효자동→김제→부안\",\"FARE_DC_CD\":\"0\",\"BUS_TYPE_NM\":\"일반\",\"TRANSP_BIZR_ABBR_NM\":\"㈜전주고속\",\"RESERVE_SEAT_CNT\":0,\"BUS_ROUTE_ID\":\"707341701801\",\"DIV_CD\":\"1\",\"DEP_TIME\":\"1540\",\"sterCode\":\"7341\",\"DISTANCE\":0,\"BLANK_CNT\":\"00\",\"GUBUN_CD\":\"EBC\",\"BUS_ORDER_DT\":\"20250624\",\"RESERVE_DC_CNT\":0,\"STATION_TOT_CNT\":2,\"ROUTE_DEP_TM\":\"1540\",\"RUN_CD\":\"1\",\"TRANSP_BIZR_ID\":\"6300012\",\"GROUP_DC_CNT\":0,\"TOT_SEAT_CNT\":\"00\",\"FARE_DC_AMT\":0,\"RESERVATION_CHK\":\"1\",\"BUS_TYPE\":\"1\",\"FARE1\":0,\"FARE0\":3200,\"FARE3\":1600,\"FARE2\":2600},{\"eterCode\":\"7009\",\"DATE_ARRAY\":\"2025-06-22 (일),2025-06-23 (월),2025-06-24 (화),2025-06-25 (수),2025-06-26 (목),2025-06-27 (금),2025-06-28 (토),2025-06-29 (일)\",\"DEP_DATE\":\"20250624\",\"BUS_ORDER_CREATE_DAYS\":7,\"REMAIN_CNT\":\"00\",\"DIST_TIME\":0,\"OPENGBN\":\"2\",\"ARR_CD\":\"1\",\"MOBILE_TICKET_CD\":\"0\",\"ROUTE_DATA\":\"효자동→김제\",\"FARE_DC_CD\":\"0\",\"BUS_TYPE_NM\":\"일반\",\"TRANSP_BIZR_ABBR_NM\":\"전북여객(주)\",\"RESERVE_SEAT_CNT\":0,\"BUS_ROUTE_ID\":\"707341700901\",\"DIV_CD\":\"1\",\"DEP_TIME\":\"1549\",\"sterCode\":\"7341\",\"DISTANCE\":0,\"BLANK_CNT\":\"00\",\"GUBUN_CD\":\"EBC\",\"BUS_ORDER_DT\":\"20250624\",\"RESERVE_DC_CNT\":0,\"STATION_TOT_CNT\":2,\"ROUTE_DEP_TM\":\"1549\",\"RUN_CD\":\"1\",\"TRANSP_BIZR_ID\":\"6300016\",\"GROUP_DC_CNT\":0,\"TOT_SEAT_CNT\":\"00\",\"FARE_DC_AMT\":0,\"RESERVATION_CHK\":\"1\",\"BUS_TYPE\":\"1\",\"FARE1\":0,\"FARE0\":3200,\"FARE3\":1600,\"FARE2\":2600},{\"eterCode\":\"7009\",\"DATE_ARRAY\":\"2025-06-22 (일),2025-06-23 (월),2025-06-24 (화),2025-06-25 (수),2025-06-26 (목),2025-06-27 (금),2025-06-28 (토),2025-06-29 (일)\",\"DEP_DATE\":\"20250624\",\"BUS_ORDER_CREATE_DAYS\":7,\"REMAIN_CNT\":\"00\",\"DIST_TIME\":0,\"OPENGBN\":\"2\",\"ARR_CD\":\"1\",\"MOBILE_TICKET_CD\":\"0\",\"ROUTE_DATA\":\"효자동→김제→부안\",\"FARE_DC_CD\":\"0\",\"BUS_TYPE_NM\":\"일반\",\"TRANSP_BIZR_ABBR_NM\":\"㈜전주고속\",\"RESERVE_SEAT_CNT\":0,\"BUS_ROUTE_ID\":\"707341701801\",\"DIV_CD\":\"1\",\"DEP_TIME\":\"1605\",\"sterCode\":\"7341\",\"DISTANCE\":0,\"BLANK_CNT\":\"00\",\"GUBUN_CD\":\"EBC\",\"BUS_ORDER_DT\":\"20250624\",\"RESERVE_DC_CNT\":0,\"STATION_TOT_CNT\":2,\"ROUTE_DEP_TM\":\"1605\",\"RUN_CD\":\"1\",\"TRANSP_BIZR_ID\":\"6300012\",\"GROUP_DC_CNT\":0,\"TOT_SEAT_CNT\":\"00\",\"FARE_DC_AMT\":0,\"RESERVATION_CHK\":\"1\",\"BUS_TYPE\":\"1\",\"FARE1\":0,\"FARE0\":3200,\"FARE3\":1600,\"FARE2\":2600},{\"eterCode\":\"7009\",\"DATE_ARRAY\":\"2025-06-22 (일),2025-06-23 (월),2025-06-24 (화),2025-06-25 (수),2025-06-26 (목),2025-06-27 (금),2025-06-28 (토),2025-06-29 (일)\",\"DEP_DATE\":\"20250624\",\"BUS_ORDER_CREATE_DAYS\":7,\"REMAIN_CNT\":\"00\",\"DIST_TIME\":0,\"OPENGBN\":\"2\",\"ARR_CD\":\"1\",\"MOBILE_TICKET_CD\":\"0\",\"ROUTE_DATA\":\"효자동→김제\",\"FARE_DC_CD\":\"0\",\"BUS_TYPE_NM\":\"일반\",\"TRANSP_BIZR_ABBR_NM\":\"전북여객(주)\",\"RESERVE_SEAT_CNT\":0,\"BUS_ROUTE_ID\":\"707341700901\",\"DIV_CD\":\"1\",\"DEP_TIME\":\"1624\",\"sterCode\":\"7341\",\"DISTANCE\":0,\"BLANK_CNT\":\"00\",\"GUBUN_CD\":\"EBC\",\"BUS_ORDER_DT\":\"20250624\",\"RESERVE_DC_CNT\":0,\"STATION_TOT_CNT\":2,\"ROUTE_DEP_TM\":\"1624\",\"RUN_CD\":\"1\",\"TRANSP_BIZR_ID\":\"6300016\",\"GROUP_DC_CNT\":0,\"TOT_SEAT_CNT\":\"00\",\"FARE_DC_AMT\":0,\"RESERVATION_CHK\":\"1\",\"BUS_TYPE\":\"1\",\"FARE1\":0,\"FARE0\":3200,\"FARE3\":1600,\"FARE2\":2600},{\"eterCode\":\"7009\",\"DATE_ARRAY\":\"2025-06-22 (일),2025-06-23 (월),2025-06-24 (화),2025-06-25 (수),2025-06-26 (목),2025-06-27 (금),2025-06-28 (토),2025-06-29 (일)\",\"DEP_DATE\":\"20250624\",\"BUS_ORDER_CREATE_DAYS\":7,\"REMAIN_CNT\":\"00\",\"DIST_TIME\":0,\"OPENGBN\":\"2\",\"ARR_CD\":\"1\",\"MOBILE_TICKET_CD\":\"0\",\"ROUTE_DATA\":\"효자동→김제→부안\",\"FARE_DC_CD\":\"0\",\"BUS_TYPE_NM\":\"일반\",\"TRANSP_BIZR_ABBR_NM\":\"㈜전주고속\",\"RESERVE_SEAT_CNT\":0,\"BUS_ROUTE_ID\":\"707341701801\",\"DIV_CD\":\"1\",\"DEP_TIME\":\"1640\",\"sterCode\":\"7341\",\"DISTANCE\":0,\"BLANK_CNT\":\"00\",\"GUBUN_CD\":\"EBC\",\"BUS_ORDER_DT\":\"20250624\",\"RESERVE_DC_CNT\":0,\"STATION_TOT_CNT\":2,\"ROUTE_DEP_TM\":\"1640\",\"RUN_CD\":\"1\",\"TRANSP_BIZR_ID\":\"6300012\",\"GROUP_DC_CNT\":0,\"TOT_SEAT_CNT\":\"00\",\"FARE_DC_AMT\":0,\"RESERVATION_CHK\":\"1\",\"BUS_TYPE\":\"1\",\"FARE1\":0,\"FARE0\":3200,\"FARE3\":1600,\"FARE2\":2600},{\"eterCode\":\"7009\",\"DATE_ARRAY\":\"2025-06-22 (일),2025-06-23 (월),2025-06-24 (화),2025-06-25 (수),2025-06-26 (목),2025-06-27 (금),2025-06-28 (토),2025-06-29 (일)\",\"DEP_DATE\":\"20250624\",\"BUS_ORDER_CREATE_DAYS\":7,\"REMAIN_CNT\":\"00\",\"DIST_TIME\":0,\"OPENGBN\":\"2\",\"ARR_CD\":\"1\",\"MOBILE_TICKET_CD\":\"0\",\"ROUTE_DATA\":\"효자동→김제\",\"FARE_DC_CD\":\"0\",\"BUS_TYPE_NM\":\"일반\",\"TRANSP_BIZR_ABBR_NM\":\"전북여객(주)\",\"RESERVE_SEAT_CNT\":0,\"BUS_ROUTE_ID\":\"707341700901\",\"DIV_CD\":\"1\",\"DEP_TIME\":\"1649\",\"sterCode\":\"7341\",\"DISTANCE\":0,\"BLANK_CNT\":\"00\",\"GUBUN_CD\":\"EBC\",\"BUS_ORDER_DT\":\"20250624\",\"RESERVE_DC_CNT\":0,\"STATION_TOT_CNT\":2,\"ROUTE_DEP_TM\":\"1649\",\"RUN_CD\":\"1\",\"TRANSP_BIZR_ID\":\"6300016\",\"GROUP_DC_CNT\":0,\"TOT_SEAT_CNT\":\"00\",\"FARE_DC_AMT\":0,\"RESERVATION_CHK\":\"1\",\"BUS_TYPE\":\"1\",\"FARE1\":0,\"FARE0\":3200,\"FARE3\":1600,\"FARE2\":2600},{\"eterCode\":\"7009\",\"DATE_ARRAY\":\"2025-06-22 (일),2025-06-23 (월),2025-06-24 (화),2025-06-25 (수),2025-06-26 (목),2025-06-27 (금),2025-06-28 (토),2025-06-29 (일)\",\"DEP_DATE\":\"20250624\",\"BUS_ORDER_CREATE_DAYS\":7,\"REMAIN_CNT\":\"00\",\"DIST_TIME\":0,\"OPENGBN\":\"2\",\"ARR_CD\":\"1\",\"MOBILE_TICKET_CD\":\"0\",\"ROUTE_DATA\":\"효자동→김제→부안\",\"FARE_DC_CD\":\"0\",\"BUS_TYPE_NM\":\"일반\",\"TRANSP_BIZR_ABBR_NM\":\"㈜전북고속\",\"RESERVE_SEAT_CNT\":0,\"BUS_ROUTE_ID\":\"707341701801\",\"DIV_CD\":\"1\",\"DEP_TIME\":\"1705\",\"sterCode\":\"7341\",\"DISTANCE\":0,\"BLANK_CNT\":\"00\",\"GUBUN_CD\":\"EBC\",\"BUS_ORDER_DT\":\"20250624\",\"RESERVE_DC_CNT\":0,\"STATION_TOT_CNT\":2,\"ROUTE_DEP_TM\":\"1705\",\"RUN_CD\":\"1\",\"TRANSP_BIZR_ID\":\"6300011\",\"GROUP_DC_CNT\":0,\"TOT_SEAT_CNT\":\"00\",\"FARE_DC_AMT\":0,\"RESERVATION_CHK\":\"1\",\"BUS_TYPE\":\"1\",\"FARE1\":0,\"FARE0\":3200,\"FARE3\":1600,\"FARE2\":2600},{\"eterCode\":\"7009\",\"DATE_ARRAY\":\"2025-06-22 (일),2025-06-23 (월),2025-06-24 (화),2025-06-25 (수),2025-06-26 (목),2025-06-27 (금),2025-06-28 (토),2025-06-29 (일)\",\"DEP_DATE\":\"20250624\",\"BUS_ORDER_CREATE_DAYS\":7,\"REMAIN_CNT\":\"00\",\"DIST_TIME\":0,\"OPENGBN\":\"2\",\"ARR_CD\":\"1\",\"MOBILE_TICKET_CD\":\"0\",\"ROUTE_DATA\":\"효자동→김제\",\"FARE_DC_CD\":\"0\",\"BUS_TYPE_NM\":\"일반\",\"TRANSP_BIZR_ABBR_NM\":\"전북여객(주)\",\"RESERVE_SEAT_CNT\":0,\"BUS_ROUTE_ID\":\"707341700901\",\"DIV_CD\":\"1\",\"DEP_TIME\":\"1724\",\"sterCode\":\"7341\",\"DISTANCE\":0,\"BLANK_CNT\":\"00\",\"GUBUN_CD\":\"EBC\",\"BUS_ORDER_DT\":\"20250624\",\"RESERVE_DC_CNT\":0,\"STATION_TOT_CNT\":2,\"ROUTE_DEP_TM\":\"1724\",\"RUN_CD\":\"1\",\"TRANSP_BIZR_ID\":\"6300016\",\"GROUP_DC_CNT\":0,\"TOT_SEAT_CNT\":\"00\",\"FARE_DC_AMT\":0,\"RESERVATION_CHK\":\"1\",\"BUS_TYPE\":\"1\",\"FARE1\":0,\"FARE0\":3200,\"FARE3\":1600,\"FARE2\":2600},{\"eterCode\":\"7009\",\"DATE_ARRAY\":\"2025-06-22 (일),2025-06-23 (월),2025-06-24 (화),2025-06-25 (수),2025-06-26 (목),2025-06-27 (금),2025-06-28 (토),2025-06-29 (일)\",\"DEP_DATE\":\"20250624\",\"BUS_ORDER_CREATE_DAYS\":7,\"REMAIN_CNT\":\"00\",\"DIST_TIME\":0,\"OPENGBN\":\"2\",\"ARR_CD\":\"1\",\"MOBILE_TICKET_CD\":\"0\",\"ROUTE_DATA\":\"효자동→김제→부안\",\"FARE_DC_CD\":\"0\",\"BUS_TYPE_NM\":\"일반\",\"TRANSP_BIZR_ABBR_NM\":\"㈜전주고속\",\"RESERVE_SEAT_CNT\":0,\"BUS_ROUTE_ID\":\"707341701801\",\"DIV_CD\":\"1\",\"DEP_TIME\":\"1755\",\"sterCode\":\"7341\",\"DISTANCE\":0,\"BLANK_CNT\":\"00\",\"GUBUN_CD\":\"EBC\",\"BUS_ORDER_DT\":\"20250624\",\"RESERVE_DC_CNT\":0,\"STATION_TOT_CNT\":2,\"ROUTE_DEP_TM\":\"1755\",\"RUN_CD\":\"1\",\"TRANSP_BIZR_ID\":\"6300012\",\"GROUP_DC_CNT\":0,\"TOT_SEAT_CNT\":\"00\",\"FARE_DC_AMT\":0,\"RESERVATION_CHK\":\"1\",\"BUS_TYPE\":\"1\",\"FARE1\":0,\"FARE0\":3200,\"FARE3\":1600,\"FARE2\":2600},{\"eterCode\":\"7009\",\"DATE_ARRAY\":\"2025-06-22 (일),2025-06-23 (월),2025-06-24 (화),2025-06-25 (수),2025-06-26 (목),2025-06-27 (금),2025-06-28 (토),2025-06-29 (일)\",\"DEP_DATE\":\"20250624\",\"BUS_ORDER_CREATE_DAYS\":7,\"REMAIN_CNT\":\"00\",\"DIST_TIME\":0,\"OPENGBN\":\"2\",\"ARR_CD\":\"1\",\"MOBILE_TICKET_CD\":\"0\",\"ROUTE_DATA\":\"효자동→김제→부안\",\"FARE_DC_CD\":\"0\",\"BUS_TYPE_NM\":\"일반\",\"TRANSP_BIZR_ABBR_NM\":\"㈜전북고속\",\"RESERVE_SEAT_CNT\":0,\"BUS_ROUTE_ID\":\"707341701801\",\"DIV_CD\":\"1\",\"DEP_TIME\":\"1815\",\"sterCode\":\"7341\",\"DISTANCE\":0,\"BLANK_CNT\":\"00\",\"GUBUN_CD\":\"EBC\",\"BUS_ORDER_DT\":\"20250624\",\"RESERVE_DC_CNT\":0,\"STATION_TOT_CNT\":2,\"ROUTE_DEP_TM\":\"1815\",\"RUN_CD\":\"1\",\"TRANSP_BIZR_ID\":\"6300011\",\"GROUP_DC_CNT\":0,\"TOT_SEAT_CNT\":\"00\",\"FARE_DC_AMT\":0,\"RESERVATION_CHK\":\"1\",\"BUS_TYPE\":\"1\",\"FARE1\":0,\"FARE0\":3200,\"FARE3\":1600,\"FARE2\":2600},{\"eterCode\":\"7009\",\"DATE_ARRAY\":\"2025-06-22 (일),2025-06-23 (월),2025-06-24 (화),2025-06-25 (수),2025-06-26 (목),2025-06-27 (금),2025-06-28 (토),2025-06-29 (일)\",\"DEP_DATE\":\"20250624\",\"BUS_ORDER_CREATE_DAYS\":7,\"REMAIN_CNT\":\"00\",\"DIST_TIME\":0,\"OPENGBN\":\"2\",\"ARR_CD\":\"1\",\"MOBILE_TICKET_CD\":\"0\",\"ROUTE_DATA\":\"효자동→김제\",\"FARE_DC_CD\":\"0\",\"BUS_TYPE_NM\":\"일반\",\"TRANSP_BIZR_ABBR_NM\":\"전북여객(주)\",\"RESERVE_SEAT_CNT\":0,\"BUS_ROUTE_ID\":\"707341700901\",\"DIV_CD\":\"1\",\"DEP_TIME\":\"1824\",\"sterCode\":\"7341\",\"DISTANCE\":0,\"BLANK_CNT\":\"00\",\"GUBUN_CD\":\"EBC\",\"BUS_ORDER_DT\":\"20250624\",\"RESERVE_DC_CNT\":0,\"STATION_TOT_CNT\":2,\"ROUTE_DEP_TM\":\"1824\",\"RUN_CD\":\"1\",\"TRANSP_BIZR_ID\":\"6300016\",\"GROUP_DC_CNT\":0,\"TOT_SEAT_CNT\":\"00\",\"FARE_DC_AMT\":0,\"RESERVATION_CHK\":\"1\",\"BUS_TYPE\":\"1\",\"FARE1\":0,\"FARE0\":3200,\"FARE3\":1600,\"FARE2\":2600},{\"eterCode\":\"7009\",\"DATE_ARRAY\":\"2025-06-22 (일),2025-06-23 (월),2025-06-24 (화),2025-06-25 (수),2025-06-26 (목),2025-06-27 (금),2025-06-28 (토),2025-06-29 (일)\",\"DEP_DATE\":\"20250624\",\"BUS_ORDER_CREATE_DAYS\":7,\"REMAIN_CNT\":\"00\",\"DIST_TIME\":0,\"OPENGBN\":\"2\",\"ARR_CD\":\"1\",\"MOBILE_TICKET_CD\":\"0\",\"ROUTE_DATA\":\"효자동→김제→부안\",\"FARE_DC_CD\":\"0\",\"BUS_TYPE_NM\":\"일반\",\"TRANSP_BIZR_ABBR_NM\":\"㈜전주고속\",\"RESERVE_SEAT_CNT\":0,\"BUS_ROUTE_ID\":\"707341701801\",\"DIV_CD\":\"1\",\"DEP_TIME\":\"1840\",\"sterCode\":\"7341\",\"DISTANCE\":0,\"BLANK_CNT\":\"00\",\"GUBUN_CD\":\"EBC\",\"BUS_ORDER_DT\":\"20250624\",\"RESERVE_DC_CNT\":0,\"STATION_TOT_CNT\":2,\"ROUTE_DEP_TM\":\"1840\",\"RUN_CD\":\"1\",\"TRANSP_BIZR_ID\":\"6300012\",\"GROUP_DC_CNT\":0,\"TOT_SEAT_CNT\":\"00\",\"FARE_DC_AMT\":0,\"RESERVATION_CHK\":\"1\",\"BUS_TYPE\":\"1\",\"FARE1\":0,\"FARE0\":3200,\"FARE3\":1600,\"FARE2\":2600},{\"eterCode\":\"7009\",\"DATE_ARRAY\":\"2025-06-22 (일),2025-06-23 (월),2025-06-24 (화),2025-06-25 (수),2025-06-26 (목),2025-06-27 (금),2025-06-28 (토),2025-06-29 (일)\",\"DEP_DATE\":\"20250624\",\"BUS_ORDER_CREATE_DAYS\":7,\"REMAIN_CNT\":\"00\",\"DIST_TIME\":0,\"OPENGBN\":\"2\",\"ARR_CD\":\"1\",\"MOBILE_TICKET_CD\":\"0\",\"ROUTE_DATA\":\"효자동→김제\",\"FARE_DC_CD\":\"0\",\"BUS_TYPE_NM\":\"일반\",\"TRANSP_BIZR_ABBR_NM\":\"전북여객(주)\",\"RESERVE_SEAT_CNT\":0,\"BUS_ROUTE_ID\":\"707341700901\",\"DIV_CD\":\"1\",\"DEP_TIME\":\"1849\",\"sterCode\":\"7341\",\"DISTANCE\":0,\"BLANK_CNT\":\"00\",\"GUBUN_CD\":\"EBC\",\"BUS_ORDER_DT\":\"20250624\",\"RESERVE_DC_CNT\":0,\"STATION_TOT_CNT\":2,\"ROUTE_DEP_TM\":\"1849\",\"RUN_CD\":\"1\",\"TRANSP_BIZR_ID\":\"6300016\",\"GROUP_DC_CNT\":0,\"TOT_SEAT_CNT\":\"00\",\"FARE_DC_AMT\":0,\"RESERVATION_CHK\":\"1\",\"BUS_TYPE\":\"1\",\"FARE1\":0,\"FARE0\":3200,\"FARE3\":1600,\"FARE2\":2600},{\"eterCode\":\"7009\",\"DATE_ARRAY\":\"2025-06-22 (일),2025-06-23 (월),2025-06-24 (화),2025-06-25 (수),2025-06-26 (목),2025-06-27 (금),2025-06-28 (토),2025-06-29 (일)\",\"DEP_DATE\":\"20250624\",\"BUS_ORDER_CREATE_DAYS\":7,\"REMAIN_CNT\":\"00\",\"DIST_TIME\":0,\"OPENGBN\":\"2\",\"ARR_CD\":\"1\",\"MOBILE_TICKET_CD\":\"0\",\"ROUTE_DATA\":\"효자동→김제→부안\",\"FARE_DC_CD\":\"0\",\"BUS_TYPE_NM\":\"일반\",\"TRANSP_BIZR_ABBR_NM\":\"㈜전주고속\",\"RESERVE_SEAT_CNT\":0,\"BUS_ROUTE_ID\":\"707341701801\",\"DIV_CD\":\"1\",\"DEP_TIME\":\"1915\",\"sterCode\":\"7341\",\"DISTANCE\":0,\"BLANK_CNT\":\"00\",\"GUBUN_CD\":\"EBC\",\"BUS_ORDER_DT\":\"20250624\",\"RESERVE_DC_CNT\":0,\"STATION_TOT_CNT\":2,\"ROUTE_DEP_TM\":\"1915\",\"RUN_CD\":\"1\",\"TRANSP_BIZR_ID\":\"6300012\",\"GROUP_DC_CNT\":0,\"TOT_SEAT_CNT\":\"00\",\"FARE_DC_AMT\":0,\"RESERVATION_CHK\":\"1\",\"BUS_TYPE\":\"1\",\"FARE1\":0,\"FARE0\":3200,\"FARE3\":1600,\"FARE2\":2600},{\"eterCode\":\"7009\",\"DATE_ARRAY\":\"2025-06-22 (일),2025-06-23 (월),2025-06-24 (화),2025-06-25 (수),2025-06-26 (목),2025-06-27 (금),2025-06-28 (토),2025-06-29 (일)\",\"DEP_DATE\":\"20250624\",\"BUS_ORDER_CREATE_DAYS\":7,\"REMAIN_CNT\":\"00\",\"DIST_TIME\":0,\"OPENGBN\":\"2\",\"ARR_CD\":\"1\",\"MOBILE_TICKET_CD\":\"0\",\"ROUTE_DATA\":\"효자동→김제\",\"FARE_DC_CD\":\"0\",\"BUS_TYPE_NM\":\"일반\",\"TRANSP_BIZR_ABBR_NM\":\"전북여객(주)\",\"RESERVE_SEAT_CNT\":0,\"BUS_ROUTE_ID\":\"707341700901\",\"DIV_CD\":\"1\",\"DEP_TIME\":\"1924\",\"sterCode\":\"7341\",\"DISTANCE\":0,\"BLANK_CNT\":\"00\",\"GUBUN_CD\":\"EBC\",\"BUS_ORDER_DT\":\"20250624\",\"RESERVE_DC_CNT\":0,\"STATION_TOT_CNT\":2,\"ROUTE_DEP_TM\":\"1924\",\"RUN_CD\":\"1\",\"TRANSP_BIZR_ID\":\"6300016\",\"GROUP_DC_CNT\":0,\"TOT_SEAT_CNT\":\"00\",\"FARE_DC_AMT\":0,\"RESERVATION_CHK\":\"1\",\"BUS_TYPE\":\"1\",\"FARE1\":0,\"FARE0\":3200,\"FARE3\":1600,\"FARE2\":2600},{\"eterCode\":\"7009\",\"DATE_ARRAY\":\"2025-06-22 (일),2025-06-23 (월),2025-06-24 (화),2025-06-25 (수),2025-06-26 (목),2025-06-27 (금),2025-06-28 (토),2025-06-29 (일)\",\"DEP_DATE\":\"20250624\",\"BUS_ORDER_CREATE_DAYS\":7,\"REMAIN_CNT\":\"00\",\"DIST_TIME\":0,\"OPENGBN\":\"2\",\"ARR_CD\":\"1\",\"MOBILE_TICKET_CD\":\"0\",\"ROUTE_DATA\":\"효자동→김제→부안\",\"FARE_DC_CD\":\"0\",\"BUS_TYPE_NM\":\"일반\",\"TRANSP_BIZR_ABBR_NM\":\"㈜전북고속\",\"RESERVE_SEAT_CNT\":0,\"BUS_ROUTE_ID\":\"707341701801\",\"DIV_CD\":\"1\",\"DEP_TIME\":\"1940\",\"sterCode\":\"7341\",\"DISTANCE\":0,\"BLANK_CNT\":\"00\",\"GUBUN_CD\":\"EBC\",\"BUS_ORDER_DT\":\"20250624\",\"RESERVE_DC_CNT\":0,\"STATION_TOT_CNT\":2,\"ROUTE_DEP_TM\":\"1940\",\"RUN_CD\":\"1\",\"TRANSP_BIZR_ID\":\"6300011\",\"GROUP_DC_CNT\":0,\"TOT_SEAT_CNT\":\"00\",\"FARE_DC_AMT\":0,\"RESERVATION_CHK\":\"1\",\"BUS_TYPE\":\"1\",\"FARE1\":0,\"FARE0\":3200,\"FARE3\":1600,\"FARE2\":2600},{\"eterCode\":\"7009\",\"DATE_ARRAY\":\"2025-06-22 (일),2025-06-23 (월),2025-06-24 (화),2025-06-25 (수),2025-06-26 (목),2025-06-27 (금),2025-06-28 (토),2025-06-29 (일)\",\"DEP_DATE\":\"20250624\",\"BUS_ORDER_CREATE_DAYS\":7,\"REMAIN_CNT\":\"00\",\"DIST_TIME\":0,\"OPENGBN\":\"2\",\"ARR_CD\":\"1\",\"MOBILE_TICKET_CD\":\"0\",\"ROUTE_DATA\":\"효자동→김제\",\"FARE_DC_CD\":\"0\",\"BUS_TYPE_NM\":\"일반\",\"TRANSP_BIZR_ABBR_NM\":\"전북여객(주)\",\"RESERVE_SEAT_CNT\":0,\"BUS_ROUTE_ID\":\"707341700901\",\"DIV_CD\":\"1\",\"DEP_TIME\":\"1949\",\"sterCode\":\"7341\",\"DISTANCE\":0,\"BLANK_CNT\":\"00\",\"GUBUN_CD\":\"EBC\",\"BUS_ORDER_DT\":\"20250624\",\"RESERVE_DC_CNT\":0,\"STATION_TOT_CNT\":2,\"ROUTE_DEP_TM\":\"1949\",\"RUN_CD\":\"1\",\"TRANSP_BIZR_ID\":\"6300016\",\"GROUP_DC_CNT\":0,\"TOT_SEAT_CNT\":\"00\",\"FARE_DC_AMT\":0,\"RESERVATION_CHK\":\"1\",\"BUS_TYPE\":\"1\",\"FARE1\":0,\"FARE0\":3200,\"FARE3\":1600,\"FARE2\":2600},{\"eterCode\":\"7009\",\"DATE_ARRAY\":\"2025-06-22 (일),2025-06-23 (월),2025-06-24 (화),2025-06-25 (수),2025-06-26 (목),2025-06-27 (금),2025-06-28 (토),2025-06-29 (일)\",\"DEP_DATE\":\"20250624\",\"BUS_ORDER_CREATE_DAYS\":7,\"REMAIN_CNT\":\"00\",\"DIST_TIME\":0,\"OPENGBN\":\"2\",\"ARR_CD\":\"1\",\"MOBILE_TICKET_CD\":\"0\",\"ROUTE_DATA\":\"효자동→김제→부안\",\"FARE_DC_CD\":\"0\",\"BUS_TYPE_NM\":\"일반\",\"TRANSP_BIZR_ABBR_NM\":\"㈜전주고속\",\"RESERVE_SEAT_CNT\":0,\"BUS_ROUTE_ID\":\"707341701801\",\"DIV_CD\":\"1\",\"DEP_TIME\":\"2015\",\"sterCode\":\"7341\",\"DISTANCE\":0,\"BLANK_CNT\":\"00\",\"GUBUN_CD\":\"EBC\",\"BUS_ORDER_DT\":\"20250624\",\"RESERVE_DC_CNT\":0,\"STATION_TOT_CNT\":2,\"ROUTE_DEP_TM\":\"2015\",\"RUN_CD\":\"1\",\"TRANSP_BIZR_ID\":\"6300012\",\"GROUP_DC_CNT\":0,\"TOT_SEAT_CNT\":\"00\",\"FARE_DC_AMT\":0,\"RESERVATION_CHK\":\"1\",\"BUS_TYPE\":\"1\",\"FARE1\":0,\"FARE0\":3200,\"FARE3\":1600,\"FARE2\":2600},{\"eterCode\":\"7009\",\"DATE_ARRAY\":\"2025-06-22 (일),2025-06-23 (월),2025-06-24 (화),2025-06-25 (수),2025-06-26 (목),2025-06-27 (금),2025-06-28 (토),2025-06-29 (일)\",\"DEP_DATE\":\"20250624\",\"BUS_ORDER_CREATE_DAYS\":7,\"REMAIN_CNT\":\"00\",\"DIST_TIME\":0,\"OPENGBN\":\"2\",\"ARR_CD\":\"1\",\"MOBILE_TICKET_CD\":\"0\",\"ROUTE_DATA\":\"효자동→김제\",\"FARE_DC_CD\":\"0\",\"BUS_TYPE_NM\":\"일반\",\"TRANSP_BIZR_ABBR_NM\":\"전북여객(주)\",\"RESERVE_SEAT_CNT\":0,\"BUS_ROUTE_ID\":\"707341700901\",\"DIV_CD\":\"1\",\"DEP_TIME\":\"2024\",\"sterCode\":\"7341\",\"DISTANCE\":0,\"BLANK_CNT\":\"00\",\"GUBUN_CD\":\"EBC\",\"BUS_ORDER_DT\":\"20250624\",\"RESERVE_DC_CNT\":0,\"STATION_TOT_CNT\":2,\"ROUTE_DEP_TM\":\"2024\",\"RUN_CD\":\"1\",\"TRANSP_BIZR_ID\":\"6300016\",\"GROUP_DC_CNT\":0,\"TOT_SEAT_CNT\":\"00\",\"FARE_DC_AMT\":0,\"RESERVATION_CHK\":\"1\",\"BUS_TYPE\":\"1\",\"FARE1\":0,\"FARE0\":3200,\"FARE3\":1600,\"FARE2\":2600},{\"eterCode\":\"7009\",\"DATE_ARRAY\":\"2025-06-22 (일),2025-06-23 (월),2025-06-24 (화),2025-06-25 (수),2025-06-26 (목),2025-06-27 (금),2025-06-28 (토),2025-06-29 (일)\",\"DEP_DATE\":\"20250624\",\"BUS_ORDER_CREATE_DAYS\":7,\"REMAIN_CNT\":\"00\",\"DIST_TIME\":0,\"OPENGBN\":\"2\",\"ARR_CD\":\"1\",\"MOBILE_TICKET_CD\":\"0\",\"ROUTE_DATA\":\"효자동→김제→부안\",\"FARE_DC_CD\":\"0\",\"BUS_TYPE_NM\":\"일반\",\"TRANSP_BIZR_ABBR_NM\":\"㈜전주고속\",\"RESERVE_SEAT_CNT\":0,\"BUS_ROUTE_ID\":\"707341701801\",\"DIV_CD\":\"1\",\"DEP_TIME\":\"2040\",\"sterCode\":\"7341\",\"DISTANCE\":0,\"BLANK_CNT\":\"00\",\"GUBUN_CD\":\"EBC\",\"BUS_ORDER_DT\":\"20250624\",\"RESERVE_DC_CNT\":0,\"STATION_TOT_CNT\":2,\"ROUTE_DEP_TM\":\"2040\",\"RUN_CD\":\"1\",\"TRANSP_BIZR_ID\":\"6300012\",\"GROUP_DC_CNT\":0,\"TOT_SEAT_CNT\":\"00\",\"FARE_DC_AMT\":0,\"RESERVATION_CHK\":\"1\",\"BUS_TYPE\":\"1\",\"FARE1\":0,\"FARE0\":3200,\"FARE3\":1600,\"FARE2\":2600},{\"eterCode\":\"7009\",\"DATE_ARRAY\":\"2025-06-22 (일),2025-06-23 (월),2025-06-24 (화),2025-06-25 (수),2025-06-26 (목),2025-06-27 (금),2025-06-28 (토),2025-06-29 (일)\",\"DEP_DATE\":\"20250624\",\"BUS_ORDER_CREATE_DAYS\":7,\"REMAIN_CNT\":\"00\",\"DIST_TIME\":0,\"OPENGBN\":\"2\",\"ARR_CD\":\"1\",\"MOBILE_TICKET_CD\":\"0\",\"ROUTE_DATA\":\"효자동→김제→부안\",\"FARE_DC_CD\":\"0\",\"BUS_TYPE_NM\":\"일반\",\"TRANSP_BIZR_ABBR_NM\":\"㈜전북고속\",\"RESERVE_SEAT_CNT\":0,\"BUS_ROUTE_ID\":\"707341701801\",\"DIV_CD\":\"1\",\"DEP_TIME\":\"2100\",\"sterCode\":\"7341\",\"DISTANCE\":0,\"BLANK_CNT\":\"00\",\"GUBUN_CD\":\"EBC\",\"BUS_ORDER_DT\":\"20250624\",\"RESERVE_DC_CNT\":0,\"STATION_TOT_CNT\":2,\"ROUTE_DEP_TM\":\"2100\",\"RUN_CD\":\"1\",\"TRANSP_BIZR_ID\":\"6300011\",\"GROUP_DC_CNT\":0,\"TOT_SEAT_CNT\":\"00\",\"FARE_DC_AMT\":0,\"RESERVATION_CHK\":\"1\",\"BUS_TYPE\":\"1\",\"FARE1\":0,\"FARE0\":3200,\"FARE3\":1600,\"FARE2\":2600},{\"eterCode\":\"7009\",\"DATE_ARRAY\":\"2025-06-22 (일),2025-06-23 (월),2025-06-24 (화),2025-06-25 (수),2025-06-26 (목),2025-06-27 (금),2025-06-28 (토),2025-06-29 (일)\",\"DEP_DATE\":\"20250624\",\"BUS_ORDER_CREATE_DAYS\":7,\"REMAIN_CNT\":\"00\",\"DIST_TIME\":0,\"OPENGBN\":\"2\",\"ARR_CD\":\"1\",\"MOBILE_TICKET_CD\":\"0\",\"ROUTE_DATA\":\"효자동→김제→부안\",\"FARE_DC_CD\":\"0\",\"BUS_TYPE_NM\":\"일반\",\"TRANSP_BIZR_ABBR_NM\":\"㈜전주고속\",\"RESERVE_SEAT_CNT\":0,\"BUS_ROUTE_ID\":\"707341701801\",\"DIV_CD\":\"1\",\"DEP_TIME\":\"2125\",\"sterCode\":\"7341\",\"DISTANCE\":0,\"BLANK_CNT\":\"00\",\"GUBUN_CD\":\"EBC\",\"BUS_ORDER_DT\":\"20250624\",\"RESERVE_DC_CNT\":0,\"STATION_TOT_CNT\":2,\"ROUTE_DEP_TM\":\"2125\",\"RUN_CD\":\"1\",\"TRANSP_BIZR_ID\":\"6300012\",\"GROUP_DC_CNT\":0,\"TOT_SEAT_CNT\":\"00\",\"FARE_DC_AMT\":0,\"RESERVATION_CHK\":\"1\",\"BUS_TYPE\":\"1\",\"FARE1\":0,\"FARE0\":3200,\"FARE3\":1600,\"FARE2\":2600},{\"eterCode\":\"7009\",\"DATE_ARRAY\":\"2025-06-22 (일),2025-06-23 (월),2025-06-24 (화),2025-06-25 (수),2025-06-26 (목),2025-06-27 (금),2025-06-28 (토),2025-06-29 (일)\",\"DEP_DATE\":\"20250624\",\"BUS_ORDER_CREATE_DAYS\":7,\"REMAIN_CNT\":\"00\",\"DIST_TIME\":0,\"OPENGBN\":\"2\",\"ARR_CD\":\"1\",\"MOBILE_TICKET_CD\":\"0\",\"ROUTE_DATA\":\"효자동→김제→부안\",\"FARE_DC_CD\":\"0\",\"BUS_TYPE_NM\":\"심야고속\",\"TRANSP_BIZR_ABBR_NM\":\"㈜전주고속\",\"RESERVE_SEAT_CNT\":0,\"BUS_ROUTE_ID\":\"707341701801\",\"DIV_CD\":\"1\",\"DEP_TIME\":\"2215\",\"sterCode\":\"7341\",\"DISTANCE\":0,\"BLANK_CNT\":\"00\",\"GUBUN_CD\":\"EBC\",\"BUS_ORDER_DT\":\"20250624\",\"RESERVE_DC_CNT\":0,\"STATION_TOT_CNT\":2,\"ROUTE_DEP_TM\":\"2215\",\"RUN_CD\":\"1\",\"TRANSP_BIZR_ID\":\"6300012\",\"GROUP_DC_CNT\":0,\"TOT_SEAT_CNT\":\"00\",\"FARE_DC_AMT\":0,\"RESERVATION_CHK\":\"1\",\"BUS_TYPE\":\"3\",\"FARE1\":0,\"FARE0\":3800,\"FARE3\":1900,\"FARE2\":3000}],\"language\":\"kr\",\"ticketDoubleList\":[]}","version":"2"}